{
  "sleep_times": [
    { "date": "일", "time": 10 },
    { "date": "월", "time": 11 },
    { "date": "화", "time": 12 },
    { "date": "수", "time": 13 },
    { "date": "목", "time": 14 },
    { "date": "금", "time": 15 },
    { "date": "토", "time": 16 }
  ],
  "signup": [
    {
      "id": "true",
      "ok": true,
      "message": "회원가입 성공"
    },
    {
      "id": "false",
      "ok": false,
      "message": "회원가입 실패"
    },
    {
      "email": "oijoij",
      "password": "oijoij",
      "nickname": "oijoij",
      "id": "YPxEcbX"
    },
    {
      "email": "oijoij",
      "password": "oijoij",
      "nickname": "oijoij",
      "id": "snX2T-O"
    },
    {
      "email": "oijoij",
      "password": "oijoij",
      "nickname": "oijoij",
      "id": "jgV7hX3"
    },
    {
      "email": "oijoij@gmail.com",
      "password": "oijoij",
      "nickname": "oijoij",
      "id": "nF-d6Dt"
    }
  ],
  "login": [
    {
      "id": "true",
      "ok": true,
      "message": "로그인 성공",
      "cookie": {
        "eamil": "naver@google.com",
        "nickname": "권유경"
      }
    },
    {
      "id": "false",
      "ok": false,
      "message": "로그인 성공"
    },
    {
      "email": "oijoij",
      "password": "oijoijoijoij",
      "id": "P-ODBur"
    },
    {
      "email": "oijoij",
      "password": "oijoijoij",
      "id": "rn1pbu_"
    },
    {
      "email": "oij",
      "password": "oij",
      "id": "_cZpL3-"
    },
    {
      "email": "",
      "password": "",
      "id": "SG7ju8L"
    },
    {
      "email": "",
      "password": "",
      "id": "o8kgo04"
    },
    {
      "email": "",
      "password": "",
      "id": "JaSdcuD"
    }
  ],
  "posts": [
    {
      "id": "2",
      "title": "아이폰X",
      "district": "북구",
      "imageURL": "https://image.zdnet.co.kr/2021/03/15/9a199a4f4d3770adff57ec09cfec4eb1.png",
      "content": "이 글은 엄청 긴 글 입니다. 진짜 길다니까요? 들어보세요. 긴 글이라고 하는데 왜 믿질 못하나요? 진짜 어이가 없네. 이 글은 엄청 긴 글 입니다. 진짜 길다니까요? 들어보세요. 긴 글이라고 하는데 왜 믿질 못하나요? 진짜 어이가 없네. 이 글은 엄청 긴 글 입니다. 진짜 길다니까요? 들어보세요. 긴 글이라고 하는데 왜 믿질 못하나요? 진짜 어이가 없네. 이 글은 엄청 긴 글 입니다. 진짜 길다니까요? 들어보세요. 긴 글이라고 하는데 왜 믿질 못하나요? 진짜 어이가 없네. ",
      "gadaoda": "oda",
      "completed": true
    },
    {
      "id": "3",
      "title": "맥북 에어",
      "district": "고산역",
      "imageURL": "https://image.zdnet.co.kr/2021/03/15/9a199a4f4d3770adff57ec09cfec4eb1.png",
      "content": "이 글은 엄청 긴 글 입니다. 진짜 길다니까요? 들어보세요. 긴 글이라고 하는데 왜 믿질 못하나요? 진짜 어이가 없네. 이 글은 엄청 긴 글 입니다. 진짜 길다니까요? 들어보세요. 긴 글이라고 하는데 왜 믿질 못하나요? 진짜 어이가 없네. 이 글은 엄청 긴 글 입니다. 진짜 길다니까요? 들어보세요. 긴 글이라고 하는데 왜 믿질 못하나요? 진짜 어이가 없네. 이 글은 엄청 긴 글 입니다. 진짜 길다니까요? 들어보세요. 긴 글이라고 하는데 왜 믿질 못하나요? 진짜 어이가 없네. ",
      "gadaoda": "oda",
      "completed": true
    },
    {
      "id": "4",
      "title": "세발 자전거",
      "district": "두류공원",
      "imageURL": "https://image.zdnet.co.kr/2021/03/15/9a199a4f4d3770adff57ec09cfec4eb1.png",
      "content": "이 글은 엄청 긴 글 입니다. 진짜 길다니까요? 들어보세요. 긴 글이라고 하는데 왜 믿질 못하나요? 진짜 어이가 없네. 이 글은 엄청 긴 글 입니다. 진짜 길다니까요? 들어보세요. 긴 글이라고 하는데 왜 믿질 못하나요? 진짜 어이가 없네. 이 글은 엄청 긴 글 입니다. 진짜 길다니까요? 들어보세요. 긴 글이라고 하는데 왜 믿질 못하나요? 진짜 어이가 없네. 이 글은 엄청 긴 글 입니다. 진짜 길다니까요? 들어보세요. 긴 글이라고 하는데 왜 믿질 못하나요? 진짜 어이가 없네. ",
      "gadaoda": "oda",
      "completed": false
    },
    {
      "id": "5",
      "title": "맥북",
      "district": "북구",
      "imageURL": "https://image.zdnet.co.kr/2021/03/15/9a199a4f4d3770adff57ec09cfec4eb1.png",
      "content": "이 글은 엄청 긴 글 입니다. 진짜 길다니까요? 들어보세요. 긴 글이라고 하는데 왜 믿질 못하나요? 진짜 어이가 없네. 이 글은 엄청 긴 글 입니다. 진짜 길다니까요? 들어보세요. 긴 글이라고 하는데 왜 믿질 못하나요? 진짜 어이가 없네. 이 글은 엄청 긴 글 입니다. 진짜 길다니까요? 들어보세요. 긴 글이라고 하는데 왜 믿질 못하나요? 진짜 어이가 없네. 이 글은 엄청 긴 글 입니다. 진짜 길다니까요? 들어보세요. 긴 글이라고 하는데 왜 믿질 못하나요? 진짜 어이가 없네. ",
      "gadaoda": "oda",
      "completed": true
    },
    {
      "id": "6",
      "title": "시계",
      "district": "북구",
      "imageURL": "https://image.zdnet.co.kr/2021/03/15/9a199a4f4d3770adff57ec09cfec4eb1.png",
      "content": "이 글은 엄청 긴 글 입니다. 진짜 길다니까요? 들어보세요. 긴 글이라고 하는데 왜 믿질 못하나요? 진짜 어이가 없네. 이 글은 엄청 긴 글 입니다. 진짜 길다니까요? 들어보세요. 긴 글이라고 하는데 왜 믿질 못하나요? 진짜 어이가 없네. 이 글은 엄청 긴 글 입니다. 진짜 길다니까요? 들어보세요. 긴 글이라고 하는데 왜 믿질 못하나요? 진짜 어이가 없네. 이 글은 엄청 긴 글 입니다. 진짜 길다니까요? 들어보세요. 긴 글이라고 하는데 왜 믿질 못하나요? 진짜 어이가 없네. ",
      "gadaoda": "gada",
      "completed": true
    },
    {
      "title": "시계",
      "district": "북구",
      "imageURL": "https://image.zdnet.co.kr/2021/03/15/9a199a4f4d3770adff57ec09cfec4eb1.png",
      "content": "이 글은 엄청 긴 글 입니다. 진짜 길다니까요? 들어보세요. 긴 글이라고 하는데 왜 믿질 못하나요? 진짜 어이가 없네. 이 글은 엄청 긴 글 입니다. 진짜 길다니까요? 들어보세요. 긴 글이라고 하는데 왜 믿질 못하나요? 진짜 어이가 없네. 이 글은 엄청 긴 글 입니다. 진짜 길다니까요? 들어보세요. 긴 글이라고 하는데 왜 믿질 못하나요? 진짜 어이가 없네. 이 글은 엄청 긴 글 입니다. 진짜 길다니까요? 들어보세요. 긴 글이라고 하는데 왜 믿질 못하나요? 진짜 어이가 없네. ",
      "id": "WTcYN87",
      "gadaoda": "gada",
      "completed": true
    },
    {
      "title": "키링",
      "district": "동성로",
      "imageURL": "https://image.zdnet.co.kr/2021/03/15/9a199a4f4d3770adff57ec09cfec4eb1.png",
      "content": "이 글은 엄청 긴 글 입니다. 진짜 길다니까요? 들어보세요. 긴 글이라고 하는데 왜 믿질 못하나요? 진짜 어이가 없네. 이 글은 엄청 긴 글 입니다. 진짜 길다니까요? 들어보세요. 긴 글이라고 하는데 왜 믿질 못하나요? 진짜 어이가 없네. 이 글은 엄청 긴 글 입니다. 진짜 길다니까요? 들어보세요. 긴 글이라고 하는데 왜 믿질 못하나요? 진짜 어이가 없네. 이 글은 엄청 긴 글 입니다. 진짜 길다니까요? 들어보세요. 긴 글이라고 하는데 왜 믿질 못하나요? 진짜 어이가 없네. ",
      "id": "pUeqzO5",
      "gadaoda": "gada",
      "completed": false
    },
    {
      "title": "카드지갑",
      "district": "대공원역",
      "imageURL": "https://image.zdnet.co.kr/2021/03/15/9a199a4f4d3770adff57ec09cfec4eb1.png",
      "content": "이 글은 엄청 긴 글 입니다. 진짜 길다니까요? 들어보세요. 긴 글이라고 하는데 왜 믿질 못하나요? 진짜 어이가 없네. 이 글은 엄청 긴 글 입니다. 진짜 길다니까요? 들어보세요. 긴 글이라고 하는데 왜 믿질 못하나요? 진짜 어이가 없네. 이 글은 엄청 긴 글 입니다. 진짜 길다니까요? 들어보세요. 긴 글이라고 하는데 왜 믿질 못하나요? 진짜 어이가 없네. 이 글은 엄청 긴 글 입니다. 진짜 길다니까요? 들어보세요. 긴 글이라고 하는데 왜 믿질 못하나요? 진짜 어이가 없네. ",
      "id": "IWusFld",
      "gadaoda": "oda",
      "completed": true
    },
    {
      "title": "충전기",
      "district": "안지랑",
      "imageURL": "https://image.zdnet.co.kr/2021/03/15/9a199a4f4d3770adff57ec09cfec4eb1.png",
      "content": "이 글은 엄청 긴 글 입니다. 진짜 길다니까요? 들어보세요. 긴 글이라고 하는데 왜 믿질 못하나요? 진짜 어이가 없네. 이 글은 엄청 긴 글 입니다. 진짜 길다니까요? 들어보세요. 긴 글이라고 하는데 왜 믿질 못하나요? 진짜 어이가 없네. 이 글은 엄청 긴 글 입니다. 진짜 길다니까요? 들어보세요. 긴 글이라고 하는데 왜 믿질 못하나요? 진짜 어이가 없네. 이 글은 엄청 긴 글 입니다. 진짜 길다니까요? 들어보세요. 긴 글이라고 하는데 왜 믿질 못하나요? 진짜 어이가 없네. ",
      "id": "36Iq4mv",
      "gadaoda": "oda",
      "completed": false
    },
    {
      "title": "충전기",
      "district": "현충로역",
      "imageURL": "https://image.zdnet.co.kr/2021/03/15/9a199a4f4d3770adff57ec09cfec4eb1.png",
      "content": "이 글은 엄청 긴 글 입니다. 진짜 길다니까요? 들어보세요. 긴 글이라고 하는데 왜 믿질 못하나요? 진짜 어이가 없네. 이 글은 엄청 긴 글 입니다. 진짜 길다니까요? 들어보세요. 긴 글이라고 하는데 왜 믿질 못하나요? 진짜 어이가 없네. 이 글은 엄청 긴 글 입니다. 진짜 길다니까요? 들어보세요. 긴 글이라고 하는데 왜 믿질 못하나요? 진짜 어이가 없네. 이 글은 엄청 긴 글 입니다. 진짜 길다니까요? 들어보세요. 긴 글이라고 하는데 왜 믿질 못하나요? 진짜 어이가 없네. ",
      "id": "uE9d58F",
      "gadaoda": "oda",
      "completed": true
    },
    {
      "title": "500원 동전",
      "district": "광장코어",
      "imageURL": "https://image.zdnet.co.kr/2021/03/15/9a199a4f4d3770adff57ec09cfec4eb1.png",
      "content": "이 글은 엄청 긴 글 입니다. 진짜 길다니까요? 들어보세요. 긴 글이라고 하는데 왜 믿질 못하나요? 진짜 어이가 없네. 이 글은 엄청 긴 글 입니다. 진짜 길다니까요? 들어보세요. 긴 글이라고 하는데 왜 믿질 못하나요? 진짜 어이가 없네. 이 글은 엄청 긴 글 입니다. 진짜 길다니까요? 들어보세요. 긴 글이라고 하는데 왜 믿질 못하나요? 진짜 어이가 없네. 이 글은 엄청 긴 글 입니다. 진짜 길다니까요? 들어보세요. 긴 글이라고 하는데 왜 믿질 못하나요? 진짜 어이가 없네. ",
      "id": "4YrizpL",
      "gadaoda": "gada",
      "completed": false
    },
    {
      "title": "안경닦이",
      "district": "대명 9동",
      "imageURL": "https://image.zdnet.co.kr/2021/03/15/9a199a4f4d3770adff57ec09cfec4eb1.png",
      "content": "이 글은 엄청 긴 글 입니다. 진짜 길다니까요? 들어보세요. 긴 글이라고 하는데 왜 믿질 못하나요? 진짜 어이가 없네. 이 글은 엄청 긴 글 입니다. 진짜 길다니까요? 들어보세요. 긴 글이라고 하는데 왜 믿질 못하나요? 진짜 어이가 없네. 이 글은 엄청 긴 글 입니다. 진짜 길다니까요? 들어보세요. 긴 글이라고 하는데 왜 믿질 못하나요? 진짜 어이가 없네. 이 글은 엄청 긴 글 입니다. 진짜 길다니까요? 들어보세요. 긴 글이라고 하는데 왜 믿질 못하나요? 진짜 어이가 없네. ",
      "id": "WhGjbO8",
      "gadaoda": "gada",
      "completed": true
    },
    {
      "title": "안경닦이",
      "district": "대명 9동",
      "imageURL": "https://image.zdnet.co.kr/2021/03/15/9a199a4f4d3770adff57ec09cfec4eb1.png",
      "content": "이 글은 엄청 긴 글 입니다. 진짜 길다니까요? 들어보세요. 긴 글이라고 하는데 왜 믿질 못하나요? 진짜 어이가 없네. 이 글은 엄청 긴 글 입니다. 진짜 길다니까요? 들어보세요. 긴 글이라고 하는데 왜 믿질 못하나요? 진짜 어이가 없네. 이 글은 엄청 긴 글 입니다. 진짜 길다니까요? 들어보세요. 긴 글이라고 하는데 왜 믿질 못하나요? 진짜 어이가 없네. 이 글은 엄청 긴 글 입니다. 진짜 길다니까요? 들어보세요. 긴 글이라고 하는데 왜 믿질 못하나요? 진짜 어이가 없네. ",
      "id": "xsMnDFq",
      "gadaoda": "gada",
      "completed": false
    },
    {
      "title": "안경닦이",
      "district": "대명 9동",
      "imageURL": "https://image.zdnet.co.kr/2021/03/15/9a199a4f4d3770adff57ec09cfec4eb1.png",
      "content": "이 글은 엄청 긴 글 입니다. 진짜 길다니까요? 들어보세요. 긴 글이라고 하는데 왜 믿질 못하나요? 진짜 어이가 없네. 이 글은 엄청 긴 글 입니다. 진짜 길다니까요? 들어보세요. 긴 글이라고 하는데 왜 믿질 못하나요? 진짜 어이가 없네. 이 글은 엄청 긴 글 입니다. 진짜 길다니까요? 들어보세요. 긴 글이라고 하는데 왜 믿질 못하나요? 진짜 어이가 없네. 이 글은 엄청 긴 글 입니다. 진짜 길다니까요? 들어보세요. 긴 글이라고 하는데 왜 믿질 못하나요? 진짜 어이가 없네. ",
      "id": "ZbC32LO",
      "gadaoda": "gada",
      "completed": true
    },
    {
      "title": "안경",
      "district": "대명 9동",
      "imageURL": "https://image.zdnet.co.kr/2021/03/15/9a199a4f4d3770adff57ec09cfec4eb1.png",
      "content": "이 글은 엄청 긴 글 입니다. 진짜 길다니까요? 들어보세요. 긴 글이라고 하는데 왜 믿질 못하나요? 진짜 어이가 없네. 이 글은 엄청 긴 글 입니다. 진짜 길다니까요? 들어보세요. 긴 글이라고 하는데 왜 믿질 못하나요? 진짜 어이가 없네. 이 글은 엄청 긴 글 입니다. 진짜 길다니까요? 들어보세요. 긴 글이라고 하는데 왜 믿질 못하나요? 진짜 어이가 없네. 이 글은 엄청 긴 글 입니다. 진짜 길다니까요? 들어보세요. 긴 글이라고 하는데 왜 믿질 못하나요? 진짜 어이가 없네. ",
      "id": "ju1muye",
      "gadaoda": "oda",
      "completed": true
    },
    {
      "title": "시곗줄",
      "district": "대명 9동",
      "imageURL": "https://image.zdnet.co.kr/2021/03/15/9a199a4f4d3770adff57ec09cfec4eb1.png",
      "content": "이 글은 엄청 긴 글 입니다. 진짜 길다니까요? 들어보세요. 긴 글이라고 하는데 왜 믿질 못하나요? 진짜 어이가 없네. 이 글은 엄청 긴 글 입니다. 진짜 길다니까요? 들어보세요. 긴 글이라고 하는데 왜 믿질 못하나요? 진짜 어이가 없네. 이 글은 엄청 긴 글 입니다. 진짜 길다니까요? 들어보세요. 긴 글이라고 하는데 왜 믿질 못하나요? 진짜 어이가 없네. 이 글은 엄청 긴 글 입니다. 진짜 길다니까요? 들어보세요. 긴 글이라고 하는데 왜 믿질 못하나요? 진짜 어이가 없네. ",
      "id": "HqqZiiD",
      "gadaoda": "oda",
      "completed": false
    },
    {
      "title": "아이폰SE",
      "district": "대명 9동",
      "imageURL": "https://image.zdnet.co.kr/2021/03/15/9a199a4f4d3770adff57ec09cfec4eb1.png",
      "content": "이 글은 엄청 긴 글 입니다. 진짜 길다니까요? 들어보세요. 긴 글이라고 하는데 왜 믿질 못하나요? 진짜 어이가 없네. 이 글은 엄청 긴 글 입니다. 진짜 길다니까요? 들어보세요. 긴 글이라고 하는데 왜 믿질 못하나요? 진짜 어이가 없네. 이 글은 엄청 긴 글 입니다. 진짜 길다니까요? 들어보세요. 긴 글이라고 하는데 왜 믿질 못하나요? 진짜 어이가 없네. 이 글은 엄청 긴 글 입니다. 진짜 길다니까요? 들어보세요. 긴 글이라고 하는데 왜 믿질 못하나요? 진짜 어이가 없네. ",
      "id": "MYn06Tc",
      "gadaoda": "gada",
      "completed": true
    },
    {
      "title": "아이폰 케이스",
      "district": "대명 9동",
      "imageURL": "https://image.zdnet.co.kr/2021/03/15/9a199a4f4d3770adff57ec09cfec4eb1.png",
      "content": "이 글은 엄청 긴 글 입니다. 진짜 길다니까요? 들어보세요. 긴 글이라고 하는데 왜 믿질 못하나요? 진짜 어이가 없네. 이 글은 엄청 긴 글 입니다. 진짜 길다니까요? 들어보세요. 긴 글이라고 하는데 왜 믿질 못하나요? 진짜 어이가 없네. 이 글은 엄청 긴 글 입니다. 진짜 길다니까요? 들어보세요. 긴 글이라고 하는데 왜 믿질 못하나요? 진짜 어이가 없네. 이 글은 엄청 긴 글 입니다. 진짜 길다니까요? 들어보세요. 긴 글이라고 하는데 왜 믿질 못하나요? 진짜 어이가 없네. ",
      "id": "kuk6q4k",
      "gadaoda": "gada",
      "completed": false
    },
    {
      "title": "에어팟 케이스",
      "district": "대명 9동",
      "imageURL": "https://image.zdnet.co.kr/2021/03/15/9a199a4f4d3770adff57ec09cfec4eb1.png",
      "content": "이 글은 엄청 긴 글 입니다. 진짜 길다니까요? 들어보세요. 긴 글이라고 하는데 왜 믿질 못하나요? 진짜 어이가 없네. 이 글은 엄청 긴 글 입니다. 진짜 길다니까요? 들어보세요. 긴 글이라고 하는데 왜 믿질 못하나요? 진짜 어이가 없네. 이 글은 엄청 긴 글 입니다. 진짜 길다니까요? 들어보세요. 긴 글이라고 하는데 왜 믿질 못하나요? 진짜 어이가 없네. 이 글은 엄청 긴 글 입니다. 진짜 길다니까요? 들어보세요. 긴 글이라고 하는데 왜 믿질 못하나요? 진짜 어이가 없네. ",
      "id": "8qw6xZi",
      "gadaoda": "oda",
      "completed": true
    },
    {
      "title": "전자담배 케이스",
      "district": "대명 9동",
      "imageURL": "https://image.zdnet.co.kr/2021/03/15/9a199a4f4d3770adff57ec09cfec4eb1.png",
      "content": "이 글은 엄청 긴 글 입니다. 진짜 길다니까요? 들어보세요. 긴 글이라고 하는데 왜 믿질 못하나요? 진짜 어이가 없네. 이 글은 엄청 긴 글 입니다. 진짜 길다니까요? 들어보세요. 긴 글이라고 하는데 왜 믿질 못하나요? 진짜 어이가 없네. 이 글은 엄청 긴 글 입니다. 진짜 길다니까요? 들어보세요. 긴 글이라고 하는데 왜 믿질 못하나요? 진짜 어이가 없네. 이 글은 엄청 긴 글 입니다. 진짜 길다니까요? 들어보세요. 긴 글이라고 하는데 왜 믿질 못하나요? 진짜 어이가 없네. ",
      "id": "jpL1isc",
      "gadaoda": "gada",
      "completed": false
    },
    {
      "title": "전자담배",
      "district": "대명 9동",
      "imageURL": "https://image.zdnet.co.kr/2021/03/15/9a199a4f4d3770adff57ec09cfec4eb1.png",
      "content": "이 글은 엄청 긴 글 입니다. 진짜 길다니까요? 들어보세요. 긴 글이라고 하는데 왜 믿질 못하나요? 진짜 어이가 없네. 이 글은 엄청 긴 글 입니다. 진짜 길다니까요? 들어보세요. 긴 글이라고 하는데 왜 믿질 못하나요? 진짜 어이가 없네. 이 글은 엄청 긴 글 입니다. 진짜 길다니까요? 들어보세요. 긴 글이라고 하는데 왜 믿질 못하나요? 진짜 어이가 없네. 이 글은 엄청 긴 글 입니다. 진짜 길다니까요? 들어보세요. 긴 글이라고 하는데 왜 믿질 못하나요? 진짜 어이가 없네. ",
      "id": "KW23yhI",
      "gadaoda": "gada",
      "completed": false
    },
    {
      "title": "지포 라이터",
      "district": "대명 9동",
      "imageURL": "https://image.zdnet.co.kr/2021/03/15/9a199a4f4d3770adff57ec09cfec4eb1.png",
      "content": "이 글은 엄청 긴 글 입니다. 진짜 길다니까요? 들어보세요. 긴 글이라고 하는데 왜 믿질 못하나요? 진짜 어이가 없네. 이 글은 엄청 긴 글 입니다. 진짜 길다니까요? 들어보세요. 긴 글이라고 하는데 왜 믿질 못하나요? 진짜 어이가 없네. 이 글은 엄청 긴 글 입니다. 진짜 길다니까요? 들어보세요. 긴 글이라고 하는데 왜 믿질 못하나요? 진짜 어이가 없네. 이 글은 엄청 긴 글 입니다. 진짜 길다니까요? 들어보세요. 긴 글이라고 하는데 왜 믿질 못하나요? 진짜 어이가 없네. ",
      "id": "UOhlKyy",
      "gadaoda": "oda",
      "completed": true
    },
    {
      "title": "명함지갑",
      "district": "대명 9동",
      "imageURL": "https://image.zdnet.co.kr/2021/03/15/9a199a4f4d3770adff57ec09cfec4eb1.png",
      "content": "이 글은 엄청 긴 글 입니다. 진짜 길다니까요? 들어보세요. 긴 글이라고 하는데 왜 믿질 못하나요? 진짜 어이가 없네. 이 글은 엄청 긴 글 입니다. 진짜 길다니까요? 들어보세요. 긴 글이라고 하는데 왜 믿질 못하나요? 진짜 어이가 없네. 이 글은 엄청 긴 글 입니다. 진짜 길다니까요? 들어보세요. 긴 글이라고 하는데 왜 믿질 못하나요? 진짜 어이가 없네. 이 글은 엄청 긴 글 입니다. 진짜 길다니까요? 들어보세요. 긴 글이라고 하는데 왜 믿질 못하나요? 진짜 어이가 없네. ",
      "id": "6C-PBBJ",
      "gadaoda": "oda",
      "completed": false
    },
    {
      "title": "차량용 방향제",
      "district": "대명 9동",
      "imageURL": "https://image.zdnet.co.kr/2021/03/15/9a199a4f4d3770adff57ec09cfec4eb1.png",
      "content": "이 글은 엄청 긴 글 입니다. 진짜 길다니까요? 들어보세요. 긴 글이라고 하는데 왜 믿질 못하나요? 진짜 어이가 없네. 이 글은 엄청 긴 글 입니다. 진짜 길다니까요? 들어보세요. 긴 글이라고 하는데 왜 믿질 못하나요? 진짜 어이가 없네. 이 글은 엄청 긴 글 입니다. 진짜 길다니까요? 들어보세요. 긴 글이라고 하는데 왜 믿질 못하나요? 진짜 어이가 없네. 이 글은 엄청 긴 글 입니다. 진짜 길다니까요? 들어보세요. 긴 글이라고 하는데 왜 믿질 못하나요? 진짜 어이가 없네. ",
      "id": "iJvmWkt",
      "gadaoda": "gada",
      "completed": true
    },
    {
      "title": "향수통",
      "district": "대명 9동",
      "imageURL": "https://image.zdnet.co.kr/2021/03/15/9a199a4f4d3770adff57ec09cfec4eb1.png",
      "content": "이 글은 엄청 긴 글 입니다. 진짜 길다니까요? 들어보세요. 긴 글이라고 하는데 왜 믿질 못하나요? 진짜 어이가 없네. 이 글은 엄청 긴 글 입니다. 진짜 길다니까요? 들어보세요. 긴 글이라고 하는데 왜 믿질 못하나요? 진짜 어이가 없네. 이 글은 엄청 긴 글 입니다. 진짜 길다니까요? 들어보세요. 긴 글이라고 하는데 왜 믿질 못하나요? 진짜 어이가 없네. 이 글은 엄청 긴 글 입니다. 진짜 길다니까요? 들어보세요. 긴 글이라고 하는데 왜 믿질 못하나요? 진짜 어이가 없네. ",
      "id": "MMKR04K",
      "gadaoda": "gada",
      "completed": false
    },
    {
      "title": "립스틱",
      "district": "대명 9동",
      "imageURL": "https://image.zdnet.co.kr/2021/03/15/9a199a4f4d3770adff57ec09cfec4eb1.png",
      "content": "이 글은 엄청 긴 글 입니다. 진짜 길다니까요? 들어보세요. 긴 글이라고 하는데 왜 믿질 못하나요? 진짜 어이가 없네. 이 글은 엄청 긴 글 입니다. 진짜 길다니까요? 들어보세요. 긴 글이라고 하는데 왜 믿질 못하나요? 진짜 어이가 없네. 이 글은 엄청 긴 글 입니다. 진짜 길다니까요? 들어보세요. 긴 글이라고 하는데 왜 믿질 못하나요? 진짜 어이가 없네. 이 글은 엄청 긴 글 입니다. 진짜 길다니까요? 들어보세요. 긴 글이라고 하는데 왜 믿질 못하나요? 진짜 어이가 없네. ",
      "id": "NjuFaiH",
      "gadaoda": "gada",
      "completed": true
    },
    {
      "title": "틴트",
      "district": "대명 9동",
      "imageURL": "https://image.zdnet.co.kr/2021/03/15/9a199a4f4d3770adff57ec09cfec4eb1.png",
      "content": "이 글은 엄청 긴 글 입니다. 진짜 길다니까요? 들어보세요. 긴 글이라고 하는데 왜 믿질 못하나요? 진짜 어이가 없네. 이 글은 엄청 긴 글 입니다. 진짜 길다니까요? 들어보세요. 긴 글이라고 하는데 왜 믿질 못하나요? 진짜 어이가 없네. 이 글은 엄청 긴 글 입니다. 진짜 길다니까요? 들어보세요. 긴 글이라고 하는데 왜 믿질 못하나요? 진짜 어이가 없네. 이 글은 엄청 긴 글 입니다. 진짜 길다니까요? 들어보세요. 긴 글이라고 하는데 왜 믿질 못하나요? 진짜 어이가 없네. ",
      "id": "BEJ0bFy",
      "gadaoda": "oda",
      "completed": true
    },
    {
      "title": "가방",
      "district": "대명 9동",
      "imageURL": "https://image.zdnet.co.kr/2021/03/15/9a199a4f4d3770adff57ec09cfec4eb1.png",
      "content": "이 글은 엄청 긴 글 입니다. 진짜 길다니까요? 들어보세요. 긴 글이라고 하는데 왜 믿질 못하나요? 진짜 어이가 없네. 이 글은 엄청 긴 글 입니다. 진짜 길다니까요? 들어보세요. 긴 글이라고 하는데 왜 믿질 못하나요? 진짜 어이가 없네. 이 글은 엄청 긴 글 입니다. 진짜 길다니까요? 들어보세요. 긴 글이라고 하는데 왜 믿질 못하나요? 진짜 어이가 없네. 이 글은 엄청 긴 글 입니다. 진짜 길다니까요? 들어보세요. 긴 글이라고 하는데 왜 믿질 못하나요? 진짜 어이가 없네. ",
      "id": "W2081AW",
      "gadaoda": "oda",
      "completed": false
    },
    {
      "title": "샤넬 핸드백",
      "district": "대명 9동",
      "imageURL": "https://image.zdnet.co.kr/2021/03/15/9a199a4f4d3770adff57ec09cfec4eb1.png",
      "content": "이 글은 엄청 긴 글 입니다. 진짜 길다니까요? 들어보세요. 긴 글이라고 하는데 왜 믿질 못하나요? 진짜 어이가 없네. 이 글은 엄청 긴 글 입니다. 진짜 길다니까요? 들어보세요. 긴 글이라고 하는데 왜 믿질 못하나요? 진짜 어이가 없네. 이 글은 엄청 긴 글 입니다. 진짜 길다니까요? 들어보세요. 긴 글이라고 하는데 왜 믿질 못하나요? 진짜 어이가 없네. 이 글은 엄청 긴 글 입니다. 진짜 길다니까요? 들어보세요. 긴 글이라고 하는데 왜 믿질 못하나요? 진짜 어이가 없네. ",
      "id": "rTdbg21",
      "gadaoda": "oda",
      "completed": true
    },
    {
      "title": "몽블랑 카드지갑",
      "district": "대명 9동",
      "imageURL": "https://image.zdnet.co.kr/2021/03/15/9a199a4f4d3770adff57ec09cfec4eb1.png",
      "content": "이 글은 엄청 긴 글 입니다. 진짜 길다니까요? 들어보세요. 긴 글이라고 하는데 왜 믿질 못하나요? 진짜 어이가 없네. 이 글은 엄청 긴 글 입니다. 진짜 길다니까요? 들어보세요. 긴 글이라고 하는데 왜 믿질 못하나요? 진짜 어이가 없네. 이 글은 엄청 긴 글 입니다. 진짜 길다니까요? 들어보세요. 긴 글이라고 하는데 왜 믿질 못하나요? 진짜 어이가 없네. 이 글은 엄청 긴 글 입니다. 진짜 길다니까요? 들어보세요. 긴 글이라고 하는데 왜 믿질 못하나요? 진짜 어이가 없네. ",
      "id": "H3si0bx",
      "gadaoda": "gada",
      "completed": true
    },
    {
      "title": "트랜치 코트",
      "district": "대명 9동",
      "imageURL": "https://image.zdnet.co.kr/2021/03/15/9a199a4f4d3770adff57ec09cfec4eb1.png",
      "content": "이 글은 엄청 긴 글 입니다. 진짜 길다니까요? 들어보세요. 긴 글이라고 하는데 왜 믿질 못하나요? 진짜 어이가 없네. 이 글은 엄청 긴 글 입니다. 진짜 길다니까요? 들어보세요. 긴 글이라고 하는데 왜 믿질 못하나요? 진짜 어이가 없네. 이 글은 엄청 긴 글 입니다. 진짜 길다니까요? 들어보세요. 긴 글이라고 하는데 왜 믿질 못하나요? 진짜 어이가 없네. 이 글은 엄청 긴 글 입니다. 진짜 길다니까요? 들어보세요. 긴 글이라고 하는데 왜 믿질 못하나요? 진짜 어이가 없네. ",
      "id": "Bd1ZriN",
      "gadaoda": "gada",
      "completed": true
    },
    {
      "title": "트랜치 코트",
      "district": "대명 9동",
      "imageURL": "https://image.zdnet.co.kr/2021/03/15/9a199a4f4d3770adff57ec09cfec4eb1.png",
      "content": "이 글은 엄청 긴 글 입니다. 진짜 길다니까요? 들어보세요. 긴 글이라고 하는데 왜 믿질 못하나요? 진짜 어이가 없네. 이 글은 엄청 긴 글 입니다. 진짜 길다니까요? 들어보세요. 긴 글이라고 하는데 왜 믿질 못하나요? 진짜 어이가 없네. 이 글은 엄청 긴 글 입니다. 진짜 길다니까요? 들어보세요. 긴 글이라고 하는데 왜 믿질 못하나요? 진짜 어이가 없네. 이 글은 엄청 긴 글 입니다. 진짜 길다니까요? 들어보세요. 긴 글이라고 하는데 왜 믿질 못하나요? 진짜 어이가 없네. ",
      "id": "a8HDL9m",
      "gadaoda": "gada",
      "completed": false
    },
    {
      "title": "나이키 바람막이",
      "district": "대명 9동",
      "imageURL": "https://image.zdnet.co.kr/2021/03/15/9a199a4f4d3770adff57ec09cfec4eb1.png",
      "content": "이 글은 엄청 긴 글 입니다. 진짜 길다니까요? 들어보세요. 긴 글이라고 하는데 왜 믿질 못하나요? 진짜 어이가 없네. 이 글은 엄청 긴 글 입니다. 진짜 길다니까요? 들어보세요. 긴 글이라고 하는데 왜 믿질 못하나요? 진짜 어이가 없네. 이 글은 엄청 긴 글 입니다. 진짜 길다니까요? 들어보세요. 긴 글이라고 하는데 왜 믿질 못하나요? 진짜 어이가 없네. 이 글은 엄청 긴 글 입니다. 진짜 길다니까요? 들어보세요. 긴 글이라고 하는데 왜 믿질 못하나요? 진짜 어이가 없네. ",
      "id": "AmX78t-",
      "gadaoda": "gada",
      "completed": false
    },
    {
      "title": "빨간색 아디다스 슬리퍼",
      "district": "대명 9동",
      "imageURL": "https://image.zdnet.co.kr/2021/03/15/9a199a4f4d3770adff57ec09cfec4eb1.png",
      "content": "이 글은 엄청 긴 글 입니다. 진짜 길다니까요? 들어보세요. 긴 글이라고 하는데 왜 믿질 못하나요? 진짜 어이가 없네. 이 글은 엄청 긴 글 입니다. 진짜 길다니까요? 들어보세요. 긴 글이라고 하는데 왜 믿질 못하나요? 진짜 어이가 없네. 이 글은 엄청 긴 글 입니다. 진짜 길다니까요? 들어보세요. 긴 글이라고 하는데 왜 믿질 못하나요? 진짜 어이가 없네. 이 글은 엄청 긴 글 입니다. 진짜 길다니까요? 들어보세요. 긴 글이라고 하는데 왜 믿질 못하나요? 진짜 어이가 없네. ",
      "id": "C5gUrM_",
      "gadaoda": "oda",
      "completed": false
    },
    {
      "title": "빨간색 아디다스 슬리퍼",
      "district": "대명 9동",
      "imageURL": "https://image.zdnet.co.kr/2021/03/15/9a199a4f4d3770adff57ec09cfec4eb1.png",
      "content": "이 글은 엄청 긴 글 입니다. 진짜 길다니까요? 들어보세요. 긴 글이라고 하는데 왜 믿질 못하나요? 진짜 어이가 없네. 이 글은 엄청 긴 글 입니다. 진짜 길다니까요? 들어보세요. 긴 글이라고 하는데 왜 믿질 못하나요? 진짜 어이가 없네. 이 글은 엄청 긴 글 입니다. 진짜 길다니까요? 들어보세요. 긴 글이라고 하는데 왜 믿질 못하나요? 진짜 어이가 없네. 이 글은 엄청 긴 글 입니다. 진짜 길다니까요? 들어보세요. 긴 글이라고 하는데 왜 믿질 못하나요? 진짜 어이가 없네. ",
      "id": "YZQbxIK",
      "gadaoda": "gada",
      "completed": true
    },
    {
      "title": "빨간색 아디다스 슬리퍼",
      "district": "대명 9동",
      "imageURL": "https://image.zdnet.co.kr/2021/03/15/9a199a4f4d3770adff57ec09cfec4eb1.png",
      "content": "이 글은 엄청 긴 글 입니다. 진짜 길다니까요? 들어보세요. 긴 글이라고 하는데 왜 믿질 못하나요? 진짜 어이가 없네. 이 글은 엄청 긴 글 입니다. 진짜 길다니까요? 들어보세요. 긴 글이라고 하는데 왜 믿질 못하나요? 진짜 어이가 없네. 이 글은 엄청 긴 글 입니다. 진짜 길다니까요? 들어보세요. 긴 글이라고 하는데 왜 믿질 못하나요? 진짜 어이가 없네. 이 글은 엄청 긴 글 입니다. 진짜 길다니까요? 들어보세요. 긴 글이라고 하는데 왜 믿질 못하나요? 진짜 어이가 없네. ",
      "id": "E8VG32G",
      "gadaoda": "gada",
      "completed": false
    },
    {
      "title": "슬리퍼",
      "district": "대명 9동",
      "imageURL": "https://image.zdnet.co.kr/2021/03/15/9a199a4f4d3770adff57ec09cfec4eb1.png",
      "content": "이 글은 엄청 긴 글 입니다. 진짜 길다니까요? 들어보세요. 긴 글이라고 하는데 왜 믿질 못하나요? 진짜 어이가 없네. 이 글은 엄청 긴 글 입니다. 진짜 길다니까요? 들어보세요. 긴 글이라고 하는데 왜 믿질 못하나요? 진짜 어이가 없네. 이 글은 엄청 긴 글 입니다. 진짜 길다니까요? 들어보세요. 긴 글이라고 하는데 왜 믿질 못하나요? 진짜 어이가 없네. 이 글은 엄청 긴 글 입니다. 진짜 길다니까요? 들어보세요. 긴 글이라고 하는데 왜 믿질 못하나요? 진짜 어이가 없네. ",
      "id": "jzFymDv",
      "gadaoda": "gada",
      "completed": true
    },
    {
      "title": "슬리퍼",
      "district": "대명 9동",
      "imageURL": "https://image.zdnet.co.kr/2021/03/15/9a199a4f4d3770adff57ec09cfec4eb1.png",
      "content": "이 글은 엄청 긴 글 입니다. 진짜 길다니까요? 들어보세요. 긴 글이라고 하는데 왜 믿질 못하나요? 진짜 어이가 없네. 이 글은 엄청 긴 글 입니다. 진짜 길다니까요? 들어보세요. 긴 글이라고 하는데 왜 믿질 못하나요? 진짜 어이가 없네. 이 글은 엄청 긴 글 입니다. 진짜 길다니까요? 들어보세요. 긴 글이라고 하는데 왜 믿질 못하나요? 진짜 어이가 없네. 이 글은 엄청 긴 글 입니다. 진짜 길다니까요? 들어보세요. 긴 글이라고 하는데 왜 믿질 못하나요? 진짜 어이가 없네. ",
      "id": "3wzQj8R",
      "gadaoda": "gada",
      "completed": false
    },
    {
      "title": "슬리퍼",
      "district": "대명 9동",
      "imageURL": "https://image.zdnet.co.kr/2021/03/15/9a199a4f4d3770adff57ec09cfec4eb1.png",
      "content": "이 글은 엄청 긴 글 입니다. 진짜 길다니까요? 들어보세요. 긴 글이라고 하는데 왜 믿질 못하나요? 진짜 어이가 없네. 이 글은 엄청 긴 글 입니다. 진짜 길다니까요? 들어보세요. 긴 글이라고 하는데 왜 믿질 못하나요? 진짜 어이가 없네. 이 글은 엄청 긴 글 입니다. 진짜 길다니까요? 들어보세요. 긴 글이라고 하는데 왜 믿질 못하나요? 진짜 어이가 없네. 이 글은 엄청 긴 글 입니다. 진짜 길다니까요? 들어보세요. 긴 글이라고 하는데 왜 믿질 못하나요? 진짜 어이가 없네. ",
      "id": "lTZGSSj",
      "gadaoda": "oda",
      "completed": false
    },
    {
      "title": "티슈",
      "district": "대명 9동",
      "imageURL": "https://image.zdnet.co.kr/2021/03/15/9a199a4f4d3770adff57ec09cfec4eb1.png",
      "content": "이 글은 엄청 긴 글 입니다. 진짜 길다니까요? 들어보세요. 긴 글이라고 하는데 왜 믿질 못하나요? 진짜 어이가 없네. 이 글은 엄청 긴 글 입니다. 진짜 길다니까요? 들어보세요. 긴 글이라고 하는데 왜 믿질 못하나요? 진짜 어이가 없네. 이 글은 엄청 긴 글 입니다. 진짜 길다니까요? 들어보세요. 긴 글이라고 하는데 왜 믿질 못하나요? 진짜 어이가 없네. 이 글은 엄청 긴 글 입니다. 진짜 길다니까요? 들어보세요. 긴 글이라고 하는데 왜 믿질 못하나요? 진짜 어이가 없네. ",
      "id": "fvWFLy_",
      "gadaoda": "oda",
      "completed": true
    },
    {
      "title": "티슈",
      "district": "대명 9동",
      "imageURL": "https://image.zdnet.co.kr/2021/03/15/9a199a4f4d3770adff57ec09cfec4eb1.png",
      "content": "이 글은 엄청 긴 글 입니다. 진짜 길다니까요? 들어보세요. 긴 글이라고 하는데 왜 믿질 못하나요? 진짜 어이가 없네. 이 글은 엄청 긴 글 입니다. 진짜 길다니까요? 들어보세요. 긴 글이라고 하는데 왜 믿질 못하나요? 진짜 어이가 없네. 이 글은 엄청 긴 글 입니다. 진짜 길다니까요? 들어보세요. 긴 글이라고 하는데 왜 믿질 못하나요? 진짜 어이가 없네. 이 글은 엄청 긴 글 입니다. 진짜 길다니까요? 들어보세요. 긴 글이라고 하는데 왜 믿질 못하나요? 진짜 어이가 없네. ",
      "id": "DoKf5jZ",
      "gadaoda": "oda",
      "completed": false
    },
    {
      "title": "티슈",
      "district": "대명 9동",
      "imageURL": "https://image.zdnet.co.kr/2021/03/15/9a199a4f4d3770adff57ec09cfec4eb1.png",
      "content": "이 글은 엄청 긴 글 입니다. 진짜 길다니까요? 들어보세요. 긴 글이라고 하는데 왜 믿질 못하나요? 진짜 어이가 없네. 이 글은 엄청 긴 글 입니다. 진짜 길다니까요? 들어보세요. 긴 글이라고 하는데 왜 믿질 못하나요? 진짜 어이가 없네. 이 글은 엄청 긴 글 입니다. 진짜 길다니까요? 들어보세요. 긴 글이라고 하는데 왜 믿질 못하나요? 진짜 어이가 없네. 이 글은 엄청 긴 글 입니다. 진짜 길다니까요? 들어보세요. 긴 글이라고 하는데 왜 믿질 못하나요? 진짜 어이가 없네. ",
      "id": "s5j_NMn",
      "gadaoda": "oda",
      "completed": true
    },
    {
      "title": "티슈",
      "district": "대명 9동",
      "imageURL": "https://image.zdnet.co.kr/2021/03/15/9a199a4f4d3770adff57ec09cfec4eb1.png",
      "content": "이 글은 엄청 긴 글 입니다. 진짜 길다니까요? 들어보세요. 긴 글이라고 하는데 왜 믿질 못하나요? 진짜 어이가 없네. 이 글은 엄청 긴 글 입니다. 진짜 길다니까요? 들어보세요. 긴 글이라고 하는데 왜 믿질 못하나요? 진짜 어이가 없네. 이 글은 엄청 긴 글 입니다. 진짜 길다니까요? 들어보세요. 긴 글이라고 하는데 왜 믿질 못하나요? 진짜 어이가 없네. 이 글은 엄청 긴 글 입니다. 진짜 길다니까요? 들어보세요. 긴 글이라고 하는데 왜 믿질 못하나요? 진짜 어이가 없네. ",
      "id": "gA7BJWP",
      "gadaoda": "oda",
      "completed": false
    },
    {
      "title": "마우스",
      "district": "대명 9동",
      "imageURL": "https://image.zdnet.co.kr/2021/03/15/9a199a4f4d3770adff57ec09cfec4eb1.png",
      "content": "이 글은 엄청 긴 글 입니다. 진짜 길다니까요? 들어보세요. 긴 글이라고 하는데 왜 믿질 못하나요? 진짜 어이가 없네. 이 글은 엄청 긴 글 입니다. 진짜 길다니까요? 들어보세요. 긴 글이라고 하는데 왜 믿질 못하나요? 진짜 어이가 없네. 이 글은 엄청 긴 글 입니다. 진짜 길다니까요? 들어보세요. 긴 글이라고 하는데 왜 믿질 못하나요? 진짜 어이가 없네. 이 글은 엄청 긴 글 입니다. 진짜 길다니까요? 들어보세요. 긴 글이라고 하는데 왜 믿질 못하나요? 진짜 어이가 없네. ",
      "id": "k3PsiTV",
      "gadaoda": "gada",
      "completed": true
    },
    {
      "title": "마우스",
      "district": "대명 9동",
      "imageURL": "https://image.zdnet.co.kr/2021/03/15/9a199a4f4d3770adff57ec09cfec4eb1.png",
      "content": "이 글은 엄청 긴 글 입니다. 진짜 길다니까요? 들어보세요. 긴 글이라고 하는데 왜 믿질 못하나요? 진짜 어이가 없네. 이 글은 엄청 긴 글 입니다. 진짜 길다니까요? 들어보세요. 긴 글이라고 하는데 왜 믿질 못하나요? 진짜 어이가 없네. 이 글은 엄청 긴 글 입니다. 진짜 길다니까요? 들어보세요. 긴 글이라고 하는데 왜 믿질 못하나요? 진짜 어이가 없네. 이 글은 엄청 긴 글 입니다. 진짜 길다니까요? 들어보세요. 긴 글이라고 하는데 왜 믿질 못하나요? 진짜 어이가 없네. ",
      "id": "rb8_qJv",
      "gadaoda": "gada",
      "completed": false
    },
    {
      "title": "남명초등학교 1학년 2반 교과서",
      "district": "대명 9동",
      "imageURL": "https://image.zdnet.co.kr/2021/03/15/9a199a4f4d3770adff57ec09cfec4eb1.png",
      "content": "이 글은 엄청 긴 글 입니다. 진짜 길다니까요? 들어보세요. 긴 글이라고 하는데 왜 믿질 못하나요? 진짜 어이가 없네. 이 글은 엄청 긴 글 입니다. 진짜 길다니까요? 들어보세요. 긴 글이라고 하는데 왜 믿질 못하나요? 진짜 어이가 없네. 이 글은 엄청 긴 글 입니다. 진짜 길다니까요? 들어보세요. 긴 글이라고 하는데 왜 믿질 못하나요? 진짜 어이가 없네. 이 글은 엄청 긴 글 입니다. 진짜 길다니까요? 들어보세요. 긴 글이라고 하는데 왜 믿질 못하나요? 진짜 어이가 없네. ",
      "id": "6aIs9E4",
      "gadaoda": "gada",
      "completed": false
    },
    {
      "title": "참고서",
      "district": "대명 9동",
      "imageURL": "https://image.zdnet.co.kr/2021/03/15/9a199a4f4d3770adff57ec09cfec4eb1.png",
      "content": "이 글은 엄청 긴 글 입니다. 진짜 길다니까요? 들어보세요. 긴 글이라고 하는데 왜 믿질 못하나요? 진짜 어이가 없네. 이 글은 엄청 긴 글 입니다. 진짜 길다니까요? 들어보세요. 긴 글이라고 하는데 왜 믿질 못하나요? 진짜 어이가 없네. 이 글은 엄청 긴 글 입니다. 진짜 길다니까요? 들어보세요. 긴 글이라고 하는데 왜 믿질 못하나요? 진짜 어이가 없네. 이 글은 엄청 긴 글 입니다. 진짜 길다니까요? 들어보세요. 긴 글이라고 하는데 왜 믿질 못하나요? 진짜 어이가 없네. ",
      "id": "IHjGfoi",
      "gadaoda": "gada",
      "completed": false
    },
    {
      "title": "참고서",
      "district": "대명 9동",
      "imageURL": "https://image.zdnet.co.kr/2021/03/15/9a199a4f4d3770adff57ec09cfec4eb1.png",
      "content": "이 글은 엄청 긴 글 입니다. 진짜 길다니까요? 들어보세요. 긴 글이라고 하는데 왜 믿질 못하나요? 진짜 어이가 없네. 이 글은 엄청 긴 글 입니다. 진짜 길다니까요? 들어보세요. 긴 글이라고 하는데 왜 믿질 못하나요? 진짜 어이가 없네. 이 글은 엄청 긴 글 입니다. 진짜 길다니까요? 들어보세요. 긴 글이라고 하는데 왜 믿질 못하나요? 진짜 어이가 없네. 이 글은 엄청 긴 글 입니다. 진짜 길다니까요? 들어보세요. 긴 글이라고 하는데 왜 믿질 못하나요? 진짜 어이가 없네. ",
      "id": "xtvbHM5",
      "gadaoda": "gada",
      "completed": false
    },
    {
      "title": "참고서",
      "district": "대명 9동",
      "imageURL": "https://image.zdnet.co.kr/2021/03/15/9a199a4f4d3770adff57ec09cfec4eb1.png",
      "content": "이 글은 엄청 긴 글 입니다. 진짜 길다니까요? 들어보세요. 긴 글이라고 하는데 왜 믿질 못하나요? 진짜 어이가 없네. 이 글은 엄청 긴 글 입니다. 진짜 길다니까요? 들어보세요. 긴 글이라고 하는데 왜 믿질 못하나요? 진짜 어이가 없네. 이 글은 엄청 긴 글 입니다. 진짜 길다니까요? 들어보세요. 긴 글이라고 하는데 왜 믿질 못하나요? 진짜 어이가 없네. 이 글은 엄청 긴 글 입니다. 진짜 길다니까요? 들어보세요. 긴 글이라고 하는데 왜 믿질 못하나요? 진짜 어이가 없네. ",
      "id": "C-tDRQG",
      "gadaoda": "gada",
      "completed": false
    },
    {
      "title": "참고서",
      "district": "대명 9동",
      "imageURL": "https://image.zdnet.co.kr/2021/03/15/9a199a4f4d3770adff57ec09cfec4eb1.png",
      "content": "이 글은 엄청 긴 글 입니다. 진짜 길다니까요? 들어보세요. 긴 글이라고 하는데 왜 믿질 못하나요? 진짜 어이가 없네. 이 글은 엄청 긴 글 입니다. 진짜 길다니까요? 들어보세요. 긴 글이라고 하는데 왜 믿질 못하나요? 진짜 어이가 없네. 이 글은 엄청 긴 글 입니다. 진짜 길다니까요? 들어보세요. 긴 글이라고 하는데 왜 믿질 못하나요? 진짜 어이가 없네. 이 글은 엄청 긴 글 입니다. 진짜 길다니까요? 들어보세요. 긴 글이라고 하는데 왜 믿질 못하나요? 진짜 어이가 없네. ",
      "id": "5IwH9lv",
      "gadaoda": "gada",
      "completed": false
    },
    {
      "title": "마우스 패드",
      "district": "대명 9동",
      "imageURL": "https://image.zdnet.co.kr/2021/03/15/9a199a4f4d3770adff57ec09cfec4eb1.png",
      "content": "이 글은 엄청 긴 글 입니다. 진짜 길다니까요? 들어보세요. 긴 글이라고 하는데 왜 믿질 못하나요? 진짜 어이가 없네. 이 글은 엄청 긴 글 입니다. 진짜 길다니까요? 들어보세요. 긴 글이라고 하는데 왜 믿질 못하나요? 진짜 어이가 없네. 이 글은 엄청 긴 글 입니다. 진짜 길다니까요? 들어보세요. 긴 글이라고 하는데 왜 믿질 못하나요? 진짜 어이가 없네. 이 글은 엄청 긴 글 입니다. 진짜 길다니까요? 들어보세요. 긴 글이라고 하는데 왜 믿질 못하나요? 진짜 어이가 없네. ",
      "id": "FJn3zqB",
      "gadaoda": "gada",
      "completed": false
    },
    {
      "title": "오토바이 헬맷",
      "district": "대명 9동",
      "imageURL": "https://image.zdnet.co.kr/2021/03/15/9a199a4f4d3770adff57ec09cfec4eb1.png",
      "content": "이 글은 엄청 긴 글 입니다. 진짜 길다니까요? 들어보세요. 긴 글이라고 하는데 왜 믿질 못하나요? 진짜 어이가 없네. 이 글은 엄청 긴 글 입니다. 진짜 길다니까요? 들어보세요. 긴 글이라고 하는데 왜 믿질 못하나요? 진짜 어이가 없네. 이 글은 엄청 긴 글 입니다. 진짜 길다니까요? 들어보세요. 긴 글이라고 하는데 왜 믿질 못하나요? 진짜 어이가 없네. 이 글은 엄청 긴 글 입니다. 진짜 길다니까요? 들어보세요. 긴 글이라고 하는데 왜 믿질 못하나요? 진짜 어이가 없네. ",
      "id": "5hoDgiF",
      "gadaoda": "gada",
      "completed": false
    },
    {
      "title": "오토바이 헬맷",
      "district": "대명 9동",
      "imageURL": "https://image.zdnet.co.kr/2021/03/15/9a199a4f4d3770adff57ec09cfec4eb1.png",
      "content": "이 글은 엄청 긴 글 입니다. 진짜 길다니까요? 들어보세요. 긴 글이라고 하는데 왜 믿질 못하나요? 진짜 어이가 없네. 이 글은 엄청 긴 글 입니다. 진짜 길다니까요? 들어보세요. 긴 글이라고 하는데 왜 믿질 못하나요? 진짜 어이가 없네. 이 글은 엄청 긴 글 입니다. 진짜 길다니까요? 들어보세요. 긴 글이라고 하는데 왜 믿질 못하나요? 진짜 어이가 없네. 이 글은 엄청 긴 글 입니다. 진짜 길다니까요? 들어보세요. 긴 글이라고 하는데 왜 믿질 못하나요? 진짜 어이가 없네. ",
      "id": "ugaL4o9",
      "gadaoda": "gada",
      "completed": false
    },
    {
      "title": "알톤 자전거",
      "district": "대명 9동",
      "imageURL": "https://image.zdnet.co.kr/2021/03/15/9a199a4f4d3770adff57ec09cfec4eb1.png",
      "content": "이 글은 엄청 긴 글 입니다. 진짜 길다니까요? 들어보세요. 긴 글이라고 하는데 왜 믿질 못하나요? 진짜 어이가 없네. 이 글은 엄청 긴 글 입니다. 진짜 길다니까요? 들어보세요. 긴 글이라고 하는데 왜 믿질 못하나요? 진짜 어이가 없네. 이 글은 엄청 긴 글 입니다. 진짜 길다니까요? 들어보세요. 긴 글이라고 하는데 왜 믿질 못하나요? 진짜 어이가 없네. 이 글은 엄청 긴 글 입니다. 진짜 길다니까요? 들어보세요. 긴 글이라고 하는데 왜 믿질 못하나요? 진짜 어이가 없네. ",
      "id": "o4rL8a7",
      "gadaoda": "oda",
      "completed": false
    },
    {
      "title": "알톤 자전거",
      "district": "대명 9동",
      "imageURL": "https://image.zdnet.co.kr/2021/03/15/9a199a4f4d3770adff57ec09cfec4eb1.png",
      "content": "이 글은 엄청 긴 글 입니다. 진짜 길다니까요? 들어보세요. 긴 글이라고 하는데 왜 믿질 못하나요? 진짜 어이가 없네. 이 글은 엄청 긴 글 입니다. 진짜 길다니까요? 들어보세요. 긴 글이라고 하는데 왜 믿질 못하나요? 진짜 어이가 없네. 이 글은 엄청 긴 글 입니다. 진짜 길다니까요? 들어보세요. 긴 글이라고 하는데 왜 믿질 못하나요? 진짜 어이가 없네. 이 글은 엄청 긴 글 입니다. 진짜 길다니까요? 들어보세요. 긴 글이라고 하는데 왜 믿질 못하나요? 진짜 어이가 없네. ",
      "id": "JHszcxR",
      "gadaoda": "oda",
      "completed": false
    },
    {
      "title": "깁슨 기타",
      "district": "대명 9동",
      "imageURL": "https://image.zdnet.co.kr/2021/03/15/9a199a4f4d3770adff57ec09cfec4eb1.png",
      "content": "이 글은 엄청 긴 글 입니다. 진짜 길다니까요? 들어보세요. 긴 글이라고 하는데 왜 믿질 못하나요? 진짜 어이가 없네. 이 글은 엄청 긴 글 입니다. 진짜 길다니까요? 들어보세요. 긴 글이라고 하는데 왜 믿질 못하나요? 진짜 어이가 없네. 이 글은 엄청 긴 글 입니다. 진짜 길다니까요? 들어보세요. 긴 글이라고 하는데 왜 믿질 못하나요? 진짜 어이가 없네. 이 글은 엄청 긴 글 입니다. 진짜 길다니까요? 들어보세요. 긴 글이라고 하는데 왜 믿질 못하나요? 진짜 어이가 없네. ",
      "id": "X0Ib5fd",
      "gadaoda": "oda",
      "completed": false
    },
    {
      "title": "깁슨 기타",
      "district": "대명 9동",
      "imageURL": "https://image.zdnet.co.kr/2021/03/15/9a199a4f4d3770adff57ec09cfec4eb1.png",
      "content": "이 글은 엄청 긴 글 입니다. 진짜 길다니까요? 들어보세요. 긴 글이라고 하는데 왜 믿질 못하나요? 진짜 어이가 없네. 이 글은 엄청 긴 글 입니다. 진짜 길다니까요? 들어보세요. 긴 글이라고 하는데 왜 믿질 못하나요? 진짜 어이가 없네. 이 글은 엄청 긴 글 입니다. 진짜 길다니까요? 들어보세요. 긴 글이라고 하는데 왜 믿질 못하나요? 진짜 어이가 없네. 이 글은 엄청 긴 글 입니다. 진짜 길다니까요? 들어보세요. 긴 글이라고 하는데 왜 믿질 못하나요? 진짜 어이가 없네. ",
      "id": "SOQ-4OC",
      "gadaoda": "gada",
      "completed": false
    },
    {
      "title": "키보드 덮개",
      "district": "대명 9동",
      "imageURL": "https://image.zdnet.co.kr/2021/03/15/9a199a4f4d3770adff57ec09cfec4eb1.png",
      "content": "이 글은 엄청 긴 글 입니다. 진짜 길다니까요? 들어보세요. 긴 글이라고 하는데 왜 믿질 못하나요? 진짜 어이가 없네. 이 글은 엄청 긴 글 입니다. 진짜 길다니까요? 들어보세요. 긴 글이라고 하는데 왜 믿질 못하나요? 진짜 어이가 없네. 이 글은 엄청 긴 글 입니다. 진짜 길다니까요? 들어보세요. 긴 글이라고 하는데 왜 믿질 못하나요? 진짜 어이가 없네. 이 글은 엄청 긴 글 입니다. 진짜 길다니까요? 들어보세요. 긴 글이라고 하는데 왜 믿질 못하나요? 진짜 어이가 없네. ",
      "id": "CBJ_GIv",
      "gadaoda": "gada",
      "completed": false
    },
    {
      "title": "키보드 덮개",
      "district": "대명 9동",
      "imageURL": "https://image.zdnet.co.kr/2021/03/15/9a199a4f4d3770adff57ec09cfec4eb1.png",
      "content": "이 글은 엄청 긴 글 입니다. 진짜 길다니까요? 들어보세요. 긴 글이라고 하는데 왜 믿질 못하나요? 진짜 어이가 없네. 이 글은 엄청 긴 글 입니다. 진짜 길다니까요? 들어보세요. 긴 글이라고 하는데 왜 믿질 못하나요? 진짜 어이가 없네. 이 글은 엄청 긴 글 입니다. 진짜 길다니까요? 들어보세요. 긴 글이라고 하는데 왜 믿질 못하나요? 진짜 어이가 없네. 이 글은 엄청 긴 글 입니다. 진짜 길다니까요? 들어보세요. 긴 글이라고 하는데 왜 믿질 못하나요? 진짜 어이가 없네. ",
      "id": "_-0BsTw",
      "gadaoda": "oda",
      "completed": false
    },
    {
      "title": "키보드 덮개",
      "district": "대명 9동",
      "imageURL": "https://image.zdnet.co.kr/2021/03/15/9a199a4f4d3770adff57ec09cfec4eb1.png",
      "content": "이 글은 엄청 긴 글 입니다. 진짜 길다니까요? 들어보세요. 긴 글이라고 하는데 왜 믿질 못하나요? 진짜 어이가 없네. 이 글은 엄청 긴 글 입니다. 진짜 길다니까요? 들어보세요. 긴 글이라고 하는데 왜 믿질 못하나요? 진짜 어이가 없네. 이 글은 엄청 긴 글 입니다. 진짜 길다니까요? 들어보세요. 긴 글이라고 하는데 왜 믿질 못하나요? 진짜 어이가 없네. 이 글은 엄청 긴 글 입니다. 진짜 길다니까요? 들어보세요. 긴 글이라고 하는데 왜 믿질 못하나요? 진짜 어이가 없네. ",
      "id": "a490v54_e3ic8v6h",
      "gadaoda": "gada",
      "completed": false
    },
    {
      "title": "덜덜",
      "content": "덜덜덜",
      "district": "east",
      "gadaoda": "oda",
      "completed": false,
      "id": "7FJCyys"
    },
    {
      "title": "덜덜",
      "content": "덜덜덜",
      "district": "east",
      "gadaoda": "gada",
      "completed": false,
      "id": "3ER_Ili"
    }
  ],
  "api": [
    {
      "comment": "어쩌다 보니 잃어버림!!!",
      "id": "2"
    },
    {
      "id": "3",
      "title": "맥북 에어",
      "district": "고산역",
      "imageURL": "https://image.zdnet.co.kr/2021/03/15/9a199a4f4d3770adff57ec09cfec4eb1.png 리중딱",
      "content": "이 글은 엄청 긴 글 입니다. 진짜 길다니까요? 들어보세요. 긴 글이라고 하는데 왜 믿질 못하나요? 진짜 어이가 없네. 이 글은 엄청 긴 글 입니다. 진짜 길다니까요? 들어보세요. 긴 글이라고 하는데 왜 믿질 못하나요? 진짜 어이가 없네. 이 글은 엄청 긴 글 입니다. 진짜 길다니까요? 들어보세요. 긴 글이라고 하는데 왜 믿질 못하나요? 진짜 어이가 없네. 이 글은 엄청 긴 글 입니다. 진짜 길다니까요? 들어보세요. 긴 글이라고 하는데 왜 믿질 못하나요? 진짜 어이가 없네. ",
      "gadaoda": "oda",
      "completed": true,
      "nickname": "맹구",
      "comments": [
        {
          "commentId": 1,
          "nickname": "ABCDEFU",
          "createdAt": "2022년 7월 1일",
          "comment": "Test코멘트 입니다!!"
        },
        {
          "commentId": 2,
          "nickname": "ABCDEFU",
          "createdAt": "2022년 7월 1일",
          "comment": "Test코멘트 입니다!!"
        },
        {
          "commentId": 3,
          "nickname": "ABCDEFU",
          "createdAt": "2022년 7월 1일",
          "comment": "Test코멘트 입니다!!"
        }
      ]
    },
    {
      "id": "4",
      "title": "세발 자전거",
      "district": "두류공원",
      "imageURL": "https://image.zdnet.co.kr/2021/03/15/9a199a4f4d3770adff57ec09cfec4eb1.png",
      "content": "이 글은 엄청 긴 글 입니다. 진짜 길다니까요? 들어보세요. 긴 글이라고 하는데 왜 믿질 못하나요? 진짜 어이가 없네. 이 글은 엄청 긴 글 입니다. 진짜 길다니까요? 들어보세요. 긴 글이라고 하는데 왜 믿질 못하나요? 진짜 어이가 없네. 이 글은 엄청 긴 글 입니다. 진짜 길다니까요? 들어보세요. 긴 글이라고 하는데 왜 믿질 못하나요? 진짜 어이가 없네. 이 글은 엄청 긴 글 입니다. 진짜 길다니까요? 들어보세요. 긴 글이라고 하는데 왜 믿질 못하나요? 진짜 어이가 없네. ",
      "gadaoda": "oda",
      "completed": false,
      "nickname": "맹구",
      "comments": [
        {
          "commentId": 1,
          "nickname": "ABCDEFU",
          "createdAt": "2022년 7월 1일",
          "comment": "Test코멘트 입니다!!"
        },
        {
          "commentId": 2,
          "nickname": "ABCDEFU",
          "createdAt": "2022년 7월 1일",
          "comment": "Test코멘트 입니다!!"
        },
        {
          "commentId": 3,
          "nickname": "ABCDEFU",
          "createdAt": "2022년 7월 1일",
          "comment": "Test코멘트 입니다!!"
        }
      ]
    },
    {
      "id": "5",
      "title": "맥북",
      "district": "북구",
      "imageURL": "https://image.zdnet.co.kr/2021/03/15/9a199a4f4d3770adff57ec09cfec4eb1.png",
      "content": "이 글은 엄청 긴 글 입니다. 진짜 길다니까요? 들어보세요. 긴 글이라고 하는데 왜 믿질 못하나요? 진짜 어이가 없네. 이 글은 엄청 긴 글 입니다. 진짜 길다니까요? 들어보세요. 긴 글이라고 하는데 왜 믿질 못하나요? 진짜 어이가 없네. 이 글은 엄청 긴 글 입니다. 진짜 길다니까요? 들어보세요. 긴 글이라고 하는데 왜 믿질 못하나요? 진짜 어이가 없네. 이 글은 엄청 긴 글 입니다. 진짜 길다니까요? 들어보세요. 긴 글이라고 하는데 왜 믿질 못하나요? 진짜 어이가 없네. ",
      "gadaoda": "oda",
      "completed": true,
      "nickname": "맹구",
      "comments": [
        {
          "commentId": 1,
          "nickname": "ABCDEFU",
          "createdAt": "2022년 7월 1일",
          "comment": "TEST TEST TEST TEST"
        },
        {
          "commentId": 2,
          "nickname": "ABCDEFU",
          "createdAt": "2022년 7월 1일",
          "comment": "TEST TEST TEST TEST"
        },
        {
          "commentId": 3,
          "nickname": "ABCDEFU",
          "createdAt": "2022년 7월 1일",
          "comment": "TEST TEST TEST TEST"
        }
      ]
    },
    {
      "id": "6",
      "title": "시계",
      "district": "북구",
      "imageURL": "https://image.zdnet.co.kr/2021/03/15/9a199a4f4d3770adff57ec09cfec4eb1.png",
      "content": "이 글은 엄청 긴 글 입니다. 진짜 길다니까요? 들어보세요. 긴 글이라고 하는데 왜 믿질 못하나요? 진짜 어이가 없네. 이 글은 엄청 긴 글 입니다. 진짜 길다니까요? 들어보세요. 긴 글이라고 하는데 왜 믿질 못하나요? 진짜 어이가 없네. 이 글은 엄청 긴 글 입니다. 진짜 길다니까요? 들어보세요. 긴 글이라고 하는데 왜 믿질 못하나요? 진짜 어이가 없네. 이 글은 엄청 긴 글 입니다. 진짜 길다니까요? 들어보세요. 긴 글이라고 하는데 왜 믿질 못하나요? 진짜 어이가 없네. ",
      "gadaoda": "gada",
      "completed": true,
      "nickname": "맹구",
      "comments": [
        {
          "commentId": 1,
          "nickname": "ABCDEFU",
          "createdAt": "2022년 7월 1일",
          "comment": "어쩌다 보니 잃어버림!"
        },
        {
          "commentId": 2,
          "nickname": "ABCDEFU",
          "createdAt": "2022년 7월 1일",
          "comment": "어쩌다 보니 잃어버림!"
        },
        {
          "commentId": 3,
          "nickname": "ABCDEFU",
          "createdAt": "2022년 7월 1일",
          "comment": "어쩌다 보니 잃어버림!"
        }
      ]
    },
    {
      "title": "시계",
      "district": "북구",
      "imageURL": "https://image.zdnet.co.kr/2021/03/15/9a199a4f4d3770adff57ec09cfec4eb1.png",
      "content": "이 글은 엄청 긴 글 입니다. 진짜 길다니까요? 들어보세요. 긴 글이라고 하는데 왜 믿질 못하나요? 진짜 어이가 없네. 이 글은 엄청 긴 글 입니다. 진짜 길다니까요? 들어보세요. 긴 글이라고 하는데 왜 믿질 못하나요? 진짜 어이가 없네. 이 글은 엄청 긴 글 입니다. 진짜 길다니까요? 들어보세요. 긴 글이라고 하는데 왜 믿질 못하나요? 진짜 어이가 없네. 이 글은 엄청 긴 글 입니다. 진짜 길다니까요? 들어보세요. 긴 글이라고 하는데 왜 믿질 못하나요? 진짜 어이가 없네. ",
      "id": "WTcYN87",
      "gadaoda": "gada",
      "completed": true,
      "nickname": "맹구",
      "comments": [
        {
          "commentId": 1,
          "nickname": "ABCDEFU",
          "createdAt": "2022년 7월 1일",
          "comment": "어쩌다 보니 잃어버림!"
        },
        {
          "commentId": 2,
          "nickname": "ABCDEFU",
          "createdAt": "2022년 7월 1일",
          "comment": "어쩌다 보니 잃어버림!"
        },
        {
          "commentId": 3,
          "nickname": "ABCDEFU",
          "createdAt": "2022년 7월 1일",
          "comment": "어쩌다 보니 잃어버림!"
        }
      ]
    },
    {
      "title": "키링",
      "district": "동성로",
      "imageURL": "https://image.zdnet.co.kr/2021/03/15/9a199a4f4d3770adff57ec09cfec4eb1.png",
      "content": "이 글은 엄청 긴 글 입니다. 진짜 길다니까요? 들어보세요. 긴 글이라고 하는데 왜 믿질 못하나요? 진짜 어이가 없네. 이 글은 엄청 긴 글 입니다. 진짜 길다니까요? 들어보세요. 긴 글이라고 하는데 왜 믿질 못하나요? 진짜 어이가 없네. 이 글은 엄청 긴 글 입니다. 진짜 길다니까요? 들어보세요. 긴 글이라고 하는데 왜 믿질 못하나요? 진짜 어이가 없네. 이 글은 엄청 긴 글 입니다. 진짜 길다니까요? 들어보세요. 긴 글이라고 하는데 왜 믿질 못하나요? 진짜 어이가 없네. ",
      "id": "pUeqzO5",
      "gadaoda": "gada",
      "completed": false,
      "nickname": "맹구",
      "comments": [
        {
          "commentId": 1,
          "nickname": "ABCDEFU",
          "createdAt": "2022년 7월 1일",
          "comment": "어쩌다 보니 잃어버림!"
        },
        {
          "commentId": 2,
          "nickname": "ABCDEFU",
          "createdAt": "2022년 7월 1일",
          "comment": "어쩌다 보니 잃어버림!"
        },
        {
          "commentId": 3,
          "nickname": "ABCDEFU",
          "createdAt": "2022년 7월 1일",
          "comment": "어쩌다 보니 잃어버림!"
        }
      ]
    },
    {
      "title": "카드지갑",
      "district": "대공원역",
      "imageURL": "https://image.zdnet.co.kr/2021/03/15/9a199a4f4d3770adff57ec09cfec4eb1.png",
      "content": "이 글은 엄청 긴 글 입니다. 진짜 길다니까요? 들어보세요. 긴 글이라고 하는데 왜 믿질 못하나요? 진짜 어이가 없네. 이 글은 엄청 긴 글 입니다. 진짜 길다니까요? 들어보세요. 긴 글이라고 하는데 왜 믿질 못하나요? 진짜 어이가 없네. 이 글은 엄청 긴 글 입니다. 진짜 길다니까요? 들어보세요. 긴 글이라고 하는데 왜 믿질 못하나요? 진짜 어이가 없네. 이 글은 엄청 긴 글 입니다. 진짜 길다니까요? 들어보세요. 긴 글이라고 하는데 왜 믿질 못하나요? 진짜 어이가 없네. ",
      "id": "IWusFld",
      "gadaoda": "oda",
      "completed": true,
      "nickname": "맹구",
      "comments": [
        {
          "commentId": 1,
          "nickname": "ABCDEFU",
          "createdAt": "2022년 7월 1일",
          "comment": "어쩌다 보니 잃어버림!"
        },
        {
          "commentId": 2,
          "nickname": "ABCDEFU",
          "createdAt": "2022년 7월 1일",
          "comment": "어쩌다 보니 잃어버림!"
        },
        {
          "commentId": 3,
          "nickname": "ABCDEFU",
          "createdAt": "2022년 7월 1일",
          "comment": "어쩌다 보니 잃어버림!"
        }
      ]
    },
    {
      "title": "충전기",
      "district": "안지랑",
      "imageURL": "https://image.zdnet.co.kr/2021/03/15/9a199a4f4d3770adff57ec09cfec4eb1.png",
      "content": "이 글은 엄청 긴 글 입니다. 진짜 길다니까요? 들어보세요. 긴 글이라고 하는데 왜 믿질 못하나요? 진짜 어이가 없네. 이 글은 엄청 긴 글 입니다. 진짜 길다니까요? 들어보세요. 긴 글이라고 하는데 왜 믿질 못하나요? 진짜 어이가 없네. 이 글은 엄청 긴 글 입니다. 진짜 길다니까요? 들어보세요. 긴 글이라고 하는데 왜 믿질 못하나요? 진짜 어이가 없네. 이 글은 엄청 긴 글 입니다. 진짜 길다니까요? 들어보세요. 긴 글이라고 하는데 왜 믿질 못하나요? 진짜 어이가 없네. ",
      "id": "36Iq4mv",
      "gadaoda": "oda",
      "completed": false,
      "nickname": "맹구",
      "comments": [
        {
          "commentId": 1,
          "nickname": "ABCDEFU",
          "createdAt": "2022년 7월 1일 11시20분29초",
          "comment": "너무 재밌어요!"
        },
        {
          "commentId": 2,
          "nickname": "ABCDEFU",
          "createdAt": "2022년 7월 1일 11시20분29초",
          "comment": "너무 있다가 없다가! 너무 있다가 없다가? 너무 있다가 없다가? 너무 있다가 없다가! 너무 있다가 없다가?너무 있다가 없다가?너무 있다가 없다가? 너무 있다가 없다가? 너무 있다가 없다가? 너무 있다가 없다가? 너무 있다가 없다가"
        },
        {
          "commentId": 3,
          "nickname": "ABCDEFU",
          "createdAt": "2022년 7월 1일 11시20분29초",
          "comment": "너무 재밌어요!"
        }
      ]
    },
    {
      "title": "충전기",
      "district": "현충로역",
      "imageURL": "https://image.zdnet.co.kr/2021/03/15/9a199a4f4d3770adff57ec09cfec4eb1.png",
      "content": "이 글은 엄청 긴 글 입니다. 진짜 길다니까요? 들어보세요. 긴 글이라고 하는데 왜 믿질 못하나요? 진짜 어이가 없네. 이 글은 엄청 긴 글 입니다. 진짜 길다니까요? 들어보세요. 긴 글이라고 하는데 왜 믿질 못하나요? 진짜 어이가 없네. 이 글은 엄청 긴 글 입니다. 진짜 길다니까요? 들어보세요. 긴 글이라고 하는데 왜 믿질 못하나요? 진짜 어이가 없네. 이 글은 엄청 긴 글 입니다. 진짜 길다니까요? 들어보세요. 긴 글이라고 하는데 왜 믿질 못하나요? 진짜 어이가 없네. ",
      "id": "uE9d58F",
      "gadaoda": "oda",
      "completed": true,
      "nickname": "맹구",
      "comments": [
        {
          "commentId": 1,
          "nickname": "ABCDEFU",
          "createdAt": "2022년 7월 1일 11시20분29초",
          "comment": "너무 재밌어요!"
        },
        {
          "commentId": 2,
          "nickname": "ABCDEFU",
          "createdAt": "2022년 7월 1일 11시20분29초",
          "comment": "너무 있다가 없다가! 너무 있다가 없다가? 너무 있다가 없다가? 너무 있다가 없다가! 너무 있다가 없다가?너무 있다가 없다가?너무 있다가 없다가? 너무 있다가 없다가? 너무 있다가 없다가? 너무 있다가 없다가? 너무 있다가 없다가"
        },
        {
          "commentId": 3,
          "nickname": "ABCDEFU",
          "createdAt": "2022년 7월 1일 11시20분29초",
          "comment": "너무 재밌어요!"
        }
      ]
    },
    {
      "title": "500원 동전",
      "district": "광장코어",
      "imageURL": "https://image.zdnet.co.kr/2021/03/15/9a199a4f4d3770adff57ec09cfec4eb1.png",
      "content": "이 글은 엄청 긴 글 입니다. 진짜 길다니까요? 들어보세요. 긴 글이라고 하는데 왜 믿질 못하나요? 진짜 어이가 없네. 이 글은 엄청 긴 글 입니다. 진짜 길다니까요? 들어보세요. 긴 글이라고 하는데 왜 믿질 못하나요? 진짜 어이가 없네. 이 글은 엄청 긴 글 입니다. 진짜 길다니까요? 들어보세요. 긴 글이라고 하는데 왜 믿질 못하나요? 진짜 어이가 없네. 이 글은 엄청 긴 글 입니다. 진짜 길다니까요? 들어보세요. 긴 글이라고 하는데 왜 믿질 못하나요? 진짜 어이가 없네. ",
      "id": "4YrizpL",
      "gadaoda": "gada",
      "completed": false,
      "nickname": "맹구",
      "comments": [
        {
          "commentId": 1,
          "nickname": "ABCDEFU",
          "createdAt": "2022년 7월 1일",
          "comment": "comment, 이렇게 남기는 거 맞나요?"
        },
        {
          "commentId": 2,
          "nickname": "ABCDEFU",
          "createdAt": "2022년 7월 1일",
          "comment": "comment, 이렇게 남기는 거 맞나요?"
        },
        {
          "commentId": 3,
          "nickname": "ABCDEFU",
          "createdAt": "2022년 7월 1일",
          "comment": "comment, 이렇게 남기는 거 맞나요?"
        }
      ]
    },
    {
      "title": "첫 번째 put 사용",
      "district": "대명 9동",
      "imageURL": "https://image.zdnet.co.kr/2021/03/15/9a199a4f4d3770adff57ec09cfec4eb1.png",
      "content": "이 글은 엄청 긴 글 입니다. 진짜 길다니까요? 들어보세요. 긴 글이라고 하는데 왜 믿질 못하나요? 진짜 어이가 없네. 이 글은 엄청 긴 글 입니다. 진짜 길다니까요? 들어보세요. 긴 글이라고 하는데 왜 믿질 못하나요? 진짜 어이가 없네. 이 글은 엄청 긴 글 입니다. 진짜 길다니까요? 들어보세요. 긴 글이라고 하는데 왜 믿질 못하나요? 진짜 어이가 없네. 이 글은 엄청 긴 글 입니다. 진짜 길다니까요? 들어보세요. 긴 글이라고 하는데 왜 믿질 못하나요? 진짜 어이가 없네. ",
      "id": "WhGjbO8",
      "gadaoda": "gada",
      "completed": true,
      "nickname": "맹구",
      "comments": [
        {
          "commentId": 1,
          "nickname": "ABCDEFU",
          "createdAt": "2022년 7월 1일",
          "comment": "이거 길 가다가 주웠어요. 근데 제가 떨어뜨린 거였음!"
        },
        {
          "commentId": 2,
          "nickname": "ABCDEFU",
          "createdAt": "2022년 7월 1일",
          "comment": "이거 길 가다가 주웠어요. 근데 제가 떨어뜨린 거였음!"
        },
        {
          "commentId": 3,
          "nickname": "ABCDEFU",
          "createdAt": "2022년 7월 1일",
          "comment": "이거 길 가다가 주웠어요. 근데 제가 떨어뜨린 거였음!"
        }
      ]
    },
    {
      "title": "안경닦이",
      "district": "대명 9동",
      "imageURL": "https://image.zdnet.co.kr/2021/03/15/9a199a4f4d3770adff57ec09cfec4eb1.png",
      "content": "이 글은 엄청 긴 글 입니다. 진짜 길다니까요? 들어보세요. 긴 글이라고 하는데 왜 믿질 못하나요? 진짜 어이가 없네. 이 글은 엄청 긴 글 입니다. 진짜 길다니까요? 들어보세요. 긴 글이라고 하는데 왜 믿질 못하나요? 진짜 어이가 없네. 이 글은 엄청 긴 글 입니다. 진짜 길다니까요? 들어보세요. 긴 글이라고 하는데 왜 믿질 못하나요? 진짜 어이가 없네. 이 글은 엄청 긴 글 입니다. 진짜 길다니까요? 들어보세요. 긴 글이라고 하는데 왜 믿질 못하나요? 진짜 어이가 없네. ",
      "id": "xsMnDFq",
      "gadaoda": "gada",
      "completed": false,
      "nickname": "맹구",
      "comments": [
        {
          "commentId": 1,
          "nickname": "ABCDEFU",
          "createdAt": "2022년 7월 1일",
          "comment": "이거 길 가다가 주웠어요. 근데 제가 떨어뜨린 거였음!"
        },
        {
          "commentId": 2,
          "nickname": "ABCDEFU",
          "createdAt": "2022년 7월 1일",
          "comment": "이거 길 가다가 주웠어요. 근데 제가 떨어뜨린 거였음!"
        },
        {
          "commentId": 3,
          "nickname": "ABCDEFU",
          "createdAt": "2022년 7월 1일",
          "comment": "이거 길 가다가 주웠어요. 근데 제가 떨어뜨린 거였음!"
        }
      ]
    },
    {
      "title": "안경닦이",
      "district": "대명 9동",
      "imageURL": "https://image.zdnet.co.kr/2021/03/15/9a199a4f4d3770adff57ec09cfec4eb1.png",
      "content": "이 글은 엄청 긴 글 입니다. 진짜 길다니까요? 들어보세요. 긴 글이라고 하는데 왜 믿질 못하나요? 진짜 어이가 없네. 이 글은 엄청 긴 글 입니다. 진짜 길다니까요? 들어보세요. 긴 글이라고 하는데 왜 믿질 못하나요? 진짜 어이가 없네. 이 글은 엄청 긴 글 입니다. 진짜 길다니까요? 들어보세요. 긴 글이라고 하는데 왜 믿질 못하나요? 진짜 어이가 없네. 이 글은 엄청 긴 글 입니다. 진짜 길다니까요? 들어보세요. 긴 글이라고 하는데 왜 믿질 못하나요? 진짜 어이가 없네. ",
      "id": "ZbC32LO",
      "gadaoda": "gada",
      "completed": true,
      "nickname": "맹구",
      "comments": [
        {
          "commentId": 1,
          "nickname": "ABCDEFU",
          "createdAt": "2022년 7월 1일",
          "comment": "이거 길 가다가 주웠어요. 근데 제가 떨어뜨린 거였음!"
        },
        {
          "commentId": 2,
          "nickname": "ABCDEFU",
          "createdAt": "2022년 7월 1일",
          "comment": "이거 길 가다가 주웠어요. 근데 제가 떨어뜨린 거였음!"
        },
        {
          "commentId": 3,
          "nickname": "ABCDEFU",
          "createdAt": "2022년 7월 1일",
          "comment": "이거 길 가다가 주웠어요. 근데 제가 떨어뜨린 거였음!"
        }
      ]
    },
    {
      "title": "안경",
      "district": "대명 9동",
      "imageURL": "https://image.zdnet.co.kr/2021/03/15/9a199a4f4d3770adff57ec09cfec4eb1.png",
      "content": "이 글은 엄청 긴 글 입니다. 진짜 길다니까요? 들어보세요. 긴 글이라고 하는데 왜 믿질 못하나요? 진짜 어이가 없네. 이 글은 엄청 긴 글 입니다. 진짜 길다니까요? 들어보세요. 긴 글이라고 하는데 왜 믿질 못하나요? 진짜 어이가 없네. 이 글은 엄청 긴 글 입니다. 진짜 길다니까요? 들어보세요. 긴 글이라고 하는데 왜 믿질 못하나요? 진짜 어이가 없네. 이 글은 엄청 긴 글 입니다. 진짜 길다니까요? 들어보세요. 긴 글이라고 하는데 왜 믿질 못하나요? 진짜 어이가 없네. ",
      "id": "ju1muye",
      "gadaoda": "oda",
      "completed": true,
      "nickname": "맹구",
      "comments": [
        {
          "commentId": 1,
          "nickname": "ABCDEFU",
          "createdAt": "2022년 7월 1일",
          "comment": "이거 길 가다가 주웠어요. 근데 제가 떨어뜨린 거였음!"
        },
        {
          "commentId": 2,
          "nickname": "ABCDEFU",
          "createdAt": "2022년 7월 1일",
          "comment": "이거 길 가다가 주웠어요. 근데 제가 떨어뜨린 거였음!"
        },
        {
          "commentId": 3,
          "nickname": "ABCDEFU",
          "createdAt": "2022년 7월 1일",
          "comment": "이거 길 가다가 주웠어요. 근데 제가 떨어뜨린 거였음!"
        }
      ]
    },
    {
      "title": "시곗줄",
      "district": "대명 9동",
      "imageURL": "https://image.zdnet.co.kr/2021/03/15/9a199a4f4d3770adff57ec09cfec4eb1.png",
      "content": "이 글은 엄청 긴 글 입니다. 진짜 길다니까요? 들어보세요. 긴 글이라고 하는데 왜 믿질 못하나요? 진짜 어이가 없네. 이 글은 엄청 긴 글 입니다. 진짜 길다니까요? 들어보세요. 긴 글이라고 하는데 왜 믿질 못하나요? 진짜 어이가 없네. 이 글은 엄청 긴 글 입니다. 진짜 길다니까요? 들어보세요. 긴 글이라고 하는데 왜 믿질 못하나요? 진짜 어이가 없네. 이 글은 엄청 긴 글 입니다. 진짜 길다니까요? 들어보세요. 긴 글이라고 하는데 왜 믿질 못하나요? 진짜 어이가 없네. ",
      "id": "HqqZiiD",
      "gadaoda": "oda",
      "completed": false,
      "nickname": "맹구",
      "comments": [
        {
          "commentId": 1,
          "nickname": "ABCDEFU",
          "createdAt": "2022년 7월 1일",
          "comment": "이거 길 가다가 주웠어요. 근데 제가 떨어뜨린 거였음!"
        },
        {
          "commentId": 2,
          "nickname": "ABCDEFU",
          "createdAt": "2022년 7월 1일",
          "comment": "이거 길 가다가 주웠어요. 근데 제가 떨어뜨린 거였음!"
        },
        {
          "commentId": 3,
          "nickname": "ABCDEFU",
          "createdAt": "2022년 7월 1일",
          "comment": "이거 길 가다가 주웠어요. 근데 제가 떨어뜨린 거였음!"
        }
      ]
    },
    {
      "title": "아이폰SE",
      "district": "대명 9동",
      "imageURL": "https://image.zdnet.co.kr/2021/03/15/9a199a4f4d3770adff57ec09cfec4eb1.png",
      "content": "이 글은 엄청 긴 글 입니다. 진짜 길다니까요? 들어보세요. 긴 글이라고 하는데 왜 믿질 못하나요? 진짜 어이가 없네. 이 글은 엄청 긴 글 입니다. 진짜 길다니까요? 들어보세요. 긴 글이라고 하는데 왜 믿질 못하나요? 진짜 어이가 없네. 이 글은 엄청 긴 글 입니다. 진짜 길다니까요? 들어보세요. 긴 글이라고 하는데 왜 믿질 못하나요? 진짜 어이가 없네. 이 글은 엄청 긴 글 입니다. 진짜 길다니까요? 들어보세요. 긴 글이라고 하는데 왜 믿질 못하나요? 진짜 어이가 없네. ",
      "id": "MYn06Tc",
      "gadaoda": "gada",
      "completed": true,
      "nickname": "맹구",
      "comments": [
        {
          "commentId": 1,
          "nickname": "ABCDEFU",
          "createdAt": "2022년 7월 1일",
          "comment": "이거 길 가다가 주웠어요. 근데 제가 떨어뜨린 거였음!"
        },
        {
          "commentId": 2,
          "nickname": "ABCDEFU",
          "createdAt": "2022년 7월 1일",
          "comment": "이거 길 가다가 주웠어요. 근데 제가 떨어뜨린 거였음!"
        },
        {
          "commentId": 3,
          "nickname": "ABCDEFU",
          "createdAt": "2022년 7월 1일",
          "comment": "이거 길 가다가 주웠어요. 근데 제가 떨어뜨린 거였음!"
        }
      ]
    },
    {
      "title": "아이폰 케이스",
      "district": "대명 9동",
      "imageURL": "https://image.zdnet.co.kr/2021/03/15/9a199a4f4d3770adff57ec09cfec4eb1.png",
      "content": "이 글은 엄청 긴 글 입니다. 진짜 길다니까요? 들어보세요. 긴 글이라고 하는데 왜 믿질 못하나요? 진짜 어이가 없네. 이 글은 엄청 긴 글 입니다. 진짜 길다니까요? 들어보세요. 긴 글이라고 하는데 왜 믿질 못하나요? 진짜 어이가 없네. 이 글은 엄청 긴 글 입니다. 진짜 길다니까요? 들어보세요. 긴 글이라고 하는데 왜 믿질 못하나요? 진짜 어이가 없네. 이 글은 엄청 긴 글 입니다. 진짜 길다니까요? 들어보세요. 긴 글이라고 하는데 왜 믿질 못하나요? 진짜 어이가 없네. ",
      "id": "kuk6q4k",
      "gadaoda": "gada",
      "completed": false,
      "nickname": "맹구",
      "comments": [
        {
          "commentId": 1,
          "nickname": "ABCDEFU",
          "createdAt": "2022년 7월 1일",
          "comment": "이거 길 가다가 주웠어요. 근데 제가 떨어뜨린 거였음!"
        },
        {
          "commentId": 2,
          "nickname": "ABCDEFU",
          "createdAt": "2022년 7월 1일",
          "comment": "이거 길 가다가 주웠어요. 근데 제가 떨어뜨린 거였음!"
        },
        {
          "commentId": 3,
          "nickname": "ABCDEFU",
          "createdAt": "2022년 7월 1일",
          "comment": "이거 길 가다가 주웠어요. 근데 제가 떨어뜨린 거였음!"
        }
      ]
    },
    {
      "title": "에어팟 케이스",
      "district": "대명 9동",
      "imageURL": "https://image.zdnet.co.kr/2021/03/15/9a199a4f4d3770adff57ec09cfec4eb1.png",
      "content": "이 글은 엄청 긴 글 입니다. 진짜 길다니까요? 들어보세요. 긴 글이라고 하는데 왜 믿질 못하나요? 진짜 어이가 없네. 이 글은 엄청 긴 글 입니다. 진짜 길다니까요? 들어보세요. 긴 글이라고 하는데 왜 믿질 못하나요? 진짜 어이가 없네. 이 글은 엄청 긴 글 입니다. 진짜 길다니까요? 들어보세요. 긴 글이라고 하는데 왜 믿질 못하나요? 진짜 어이가 없네. 이 글은 엄청 긴 글 입니다. 진짜 길다니까요? 들어보세요. 긴 글이라고 하는데 왜 믿질 못하나요? 진짜 어이가 없네. ",
      "id": "8qw6xZi",
      "gadaoda": "oda",
      "completed": true,
      "nickname": "맹구",
      "comments": [
        {
          "commentId": 1,
          "nickname": "ABCDEFU",
          "createdAt": "2022년 7월 1일",
          "comment": "이거 길 가다가 주웠어요. 근데 제가 떨어뜨린 거였음!"
        },
        {
          "commentId": 2,
          "nickname": "ABCDEFU",
          "createdAt": "2022년 7월 1일",
          "comment": "이거 길 가다가 주웠어요. 근데 제가 떨어뜨린 거였음!"
        },
        {
          "commentId": 3,
          "nickname": "ABCDEFU",
          "createdAt": "2022년 7월 1일",
          "comment": "이거 길 가다가 주웠어요. 근데 제가 떨어뜨린 거였음!"
        }
      ]
    },
    {
      "title": "전자담배 케이스",
      "district": "대명 9동",
      "imageURL": "https://image.zdnet.co.kr/2021/03/15/9a199a4f4d3770adff57ec09cfec4eb1.png",
      "content": "이 글은 엄청 긴 글 입니다. 진짜 길다니까요? 들어보세요. 긴 글이라고 하는데 왜 믿질 못하나요? 진짜 어이가 없네. 이 글은 엄청 긴 글 입니다. 진짜 길다니까요? 들어보세요. 긴 글이라고 하는데 왜 믿질 못하나요? 진짜 어이가 없네. 이 글은 엄청 긴 글 입니다. 진짜 길다니까요? 들어보세요. 긴 글이라고 하는데 왜 믿질 못하나요? 진짜 어이가 없네. 이 글은 엄청 긴 글 입니다. 진짜 길다니까요? 들어보세요. 긴 글이라고 하는데 왜 믿질 못하나요? 진짜 어이가 없네. ",
      "id": "jpL1isc",
      "gadaoda": "gada",
      "completed": false,
      "nickname": "맹구",
      "comments": [
        {
          "commentId": 1,
          "nickname": "ABCDEFU",
          "createdAt": "2022년 7월 1일",
          "comment": "이거 길 가다가 주웠어요. 근데 제가 떨어뜨린 거였음!"
        },
        {
          "commentId": 2,
          "nickname": "ABCDEFU",
          "createdAt": "2022년 7월 1일",
          "comment": "이거 길 가다가 주웠어요. 근데 제가 떨어뜨린 거였음!"
        },
        {
          "commentId": 3,
          "nickname": "ABCDEFU",
          "createdAt": "2022년 7월 1일",
          "comment": "이거 길 가다가 주웠어요. 근데 제가 떨어뜨린 거였음!"
        }
      ]
    },
    {
      "title": "전자담배",
      "district": "대명 9동",
      "imageURL": "https://image.zdnet.co.kr/2021/03/15/9a199a4f4d3770adff57ec09cfec4eb1.png",
      "content": "이 글은 엄청 긴 글 입니다. 진짜 길다니까요? 들어보세요. 긴 글이라고 하는데 왜 믿질 못하나요? 진짜 어이가 없네. 이 글은 엄청 긴 글 입니다. 진짜 길다니까요? 들어보세요. 긴 글이라고 하는데 왜 믿질 못하나요? 진짜 어이가 없네. 이 글은 엄청 긴 글 입니다. 진짜 길다니까요? 들어보세요. 긴 글이라고 하는데 왜 믿질 못하나요? 진짜 어이가 없네. 이 글은 엄청 긴 글 입니다. 진짜 길다니까요? 들어보세요. 긴 글이라고 하는데 왜 믿질 못하나요? 진짜 어이가 없네. ",
      "id": "KW23yhI",
      "gadaoda": "gada",
      "completed": false,
      "nickname": "맹구",
      "comments": [
        {
          "commentId": 1,
          "nickname": "ABCDEFU",
          "createdAt": "2022년 7월 1일",
          "comment": "이거 길 가다가 주웠어요. 근데 제가 떨어뜨린 거였음!"
        },
        {
          "commentId": 2,
          "nickname": "ABCDEFU",
          "createdAt": "2022년 7월 1일",
          "comment": "이거 길 가다가 주웠어요. 근데 제가 떨어뜨린 거였음!"
        },
        {
          "commentId": 3,
          "nickname": "ABCDEFU",
          "createdAt": "2022년 7월 1일",
          "comment": "이거 길 가다가 주웠어요. 근데 제가 떨어뜨린 거였음!"
        }
      ]
    },
    {
      "title": "지포 라이터",
      "district": "대명 9동",
      "imageURL": "https://image.zdnet.co.kr/2021/03/15/9a199a4f4d3770adff57ec09cfec4eb1.png",
      "content": "이 글은 엄청 긴 글 입니다. 진짜 길다니까요? 들어보세요. 긴 글이라고 하는데 왜 믿질 못하나요? 진짜 어이가 없네. 이 글은 엄청 긴 글 입니다. 진짜 길다니까요? 들어보세요. 긴 글이라고 하는데 왜 믿질 못하나요? 진짜 어이가 없네. 이 글은 엄청 긴 글 입니다. 진짜 길다니까요? 들어보세요. 긴 글이라고 하는데 왜 믿질 못하나요? 진짜 어이가 없네. 이 글은 엄청 긴 글 입니다. 진짜 길다니까요? 들어보세요. 긴 글이라고 하는데 왜 믿질 못하나요? 진짜 어이가 없네. ",
      "id": "UOhlKyy",
      "gadaoda": "oda",
      "completed": true,
      "nickname": "맹구",
      "comments": [
        {
          "commentId": 1,
          "nickname": "ABCDEFU",
          "createdAt": "2022년 7월 1일",
          "comment": "이거 길 가다가 주웠어요. 근데 제가 떨어뜨린 거였음!"
        },
        {
          "commentId": 2,
          "nickname": "ABCDEFU",
          "createdAt": "2022년 7월 1일",
          "comment": "이거 길 가다가 주웠어요. 근데 제가 떨어뜨린 거였음!"
        },
        {
          "commentId": 3,
          "nickname": "ABCDEFU",
          "createdAt": "2022년 7월 1일",
          "comment": "이거 길 가다가 주웠어요. 근데 제가 떨어뜨린 거였음!"
        }
      ]
    },
    {
      "title": "명함지갑",
      "district": "대명 9동",
      "imageURL": "https://image.zdnet.co.kr/2021/03/15/9a199a4f4d3770adff57ec09cfec4eb1.png",
      "content": "이 글은 엄청 긴 글 입니다. 진짜 길다니까요? 들어보세요. 긴 글이라고 하는데 왜 믿질 못하나요? 진짜 어이가 없네. 이 글은 엄청 긴 글 입니다. 진짜 길다니까요? 들어보세요. 긴 글이라고 하는데 왜 믿질 못하나요? 진짜 어이가 없네. 이 글은 엄청 긴 글 입니다. 진짜 길다니까요? 들어보세요. 긴 글이라고 하는데 왜 믿질 못하나요? 진짜 어이가 없네. 이 글은 엄청 긴 글 입니다. 진짜 길다니까요? 들어보세요. 긴 글이라고 하는데 왜 믿질 못하나요? 진짜 어이가 없네. ",
      "id": "6C-PBBJ",
      "gadaoda": "oda",
      "completed": false,
      "nickname": "맹구",
      "comments": [
        {
          "commentId": 1,
          "nickname": "ABCDEFU",
          "createdAt": "2022년 7월 1일",
          "comment": "이거 길 가다가 주웠어요. 근데 제가 떨어뜨린 거였음!"
        },
        {
          "commentId": 2,
          "nickname": "ABCDEFU",
          "createdAt": "2022년 7월 1일",
          "comment": "이거 길 가다가 주웠어요. 근데 제가 떨어뜨린 거였음!"
        },
        {
          "commentId": 3,
          "nickname": "ABCDEFU",
          "createdAt": "2022년 7월 1일",
          "comment": "이거 길 가다가 주웠어요. 근데 제가 떨어뜨린 거였음!"
        }
      ]
    },
    {
      "title": "차량용 방향제",
      "district": "대명 9동",
      "imageURL": "https://image.zdnet.co.kr/2021/03/15/9a199a4f4d3770adff57ec09cfec4eb1.png",
      "content": "이 글은 엄청 긴 글 입니다. 진짜 길다니까요? 들어보세요. 긴 글이라고 하는데 왜 믿질 못하나요? 진짜 어이가 없네. 이 글은 엄청 긴 글 입니다. 진짜 길다니까요? 들어보세요. 긴 글이라고 하는데 왜 믿질 못하나요? 진짜 어이가 없네. 이 글은 엄청 긴 글 입니다. 진짜 길다니까요? 들어보세요. 긴 글이라고 하는데 왜 믿질 못하나요? 진짜 어이가 없네. 이 글은 엄청 긴 글 입니다. 진짜 길다니까요? 들어보세요. 긴 글이라고 하는데 왜 믿질 못하나요? 진짜 어이가 없네. ",
      "id": "iJvmWkt",
      "gadaoda": "gada",
      "completed": true,
      "nickname": "맹구",
      "comments": [
        {
          "commentId": 1,
          "nickname": "ABCDEFU",
          "createdAt": "2022년 7월 1일",
          "comment": "이거 길 가다가 주웠어요. 근데 제가 떨어뜨린 거였음!"
        },
        {
          "commentId": 2,
          "nickname": "ABCDEFU",
          "createdAt": "2022년 7월 1일",
          "comment": "이거 길 가다가 주웠어요. 근데 제가 떨어뜨린 거였음!"
        },
        {
          "commentId": 3,
          "nickname": "ABCDEFU",
          "createdAt": "2022년 7월 1일",
          "comment": "이거 길 가다가 주웠어요. 근데 제가 떨어뜨린 거였음!"
        }
      ]
    },
    {
      "title": "향수통",
      "district": "대명 9동",
      "imageURL": "https://image.zdnet.co.kr/2021/03/15/9a199a4f4d3770adff57ec09cfec4eb1.png",
      "content": "이 글은 엄청 긴 글 입니다. 진짜 길다니까요? 들어보세요. 긴 글이라고 하는데 왜 믿질 못하나요? 진짜 어이가 없네. 이 글은 엄청 긴 글 입니다. 진짜 길다니까요? 들어보세요. 긴 글이라고 하는데 왜 믿질 못하나요? 진짜 어이가 없네. 이 글은 엄청 긴 글 입니다. 진짜 길다니까요? 들어보세요. 긴 글이라고 하는데 왜 믿질 못하나요? 진짜 어이가 없네. 이 글은 엄청 긴 글 입니다. 진짜 길다니까요? 들어보세요. 긴 글이라고 하는데 왜 믿질 못하나요? 진짜 어이가 없네. ",
      "id": "MMKR04K",
      "gadaoda": "gada",
      "completed": false,
      "nickname": "맹구",
      "comments": [
        {
          "commentId": 1,
          "nickname": "ABCDEFU",
          "createdAt": "2022년 7월 1일",
          "comment": "이거 길 가다가 주웠어요. 근데 제가 떨어뜨린 거였음!"
        },
        {
          "commentId": 2,
          "nickname": "ABCDEFU",
          "createdAt": "2022년 7월 1일",
          "comment": "이거 길 가다가 주웠어요. 근데 제가 떨어뜨린 거였음!"
        },
        {
          "commentId": 3,
          "nickname": "ABCDEFU",
          "createdAt": "2022년 7월 1일",
          "comment": "이거 길 가다가 주웠어요. 근데 제가 떨어뜨린 거였음!"
        }
      ]
    },
    {
      "title": "립스틱",
      "district": "대명 9동",
      "imageURL": "https://image.zdnet.co.kr/2021/03/15/9a199a4f4d3770adff57ec09cfec4eb1.png",
      "content": "이 글은 엄청 긴 글 입니다. 진짜 길다니까요? 들어보세요. 긴 글이라고 하는데 왜 믿질 못하나요? 진짜 어이가 없네. 이 글은 엄청 긴 글 입니다. 진짜 길다니까요? 들어보세요. 긴 글이라고 하는데 왜 믿질 못하나요? 진짜 어이가 없네. 이 글은 엄청 긴 글 입니다. 진짜 길다니까요? 들어보세요. 긴 글이라고 하는데 왜 믿질 못하나요? 진짜 어이가 없네. 이 글은 엄청 긴 글 입니다. 진짜 길다니까요? 들어보세요. 긴 글이라고 하는데 왜 믿질 못하나요? 진짜 어이가 없네. ",
      "id": "NjuFaiH",
      "gadaoda": "gada",
      "completed": true,
      "nickname": "맹구",
      "comments": [
        {
          "commentId": 1,
          "nickname": "ABCDEFU",
          "createdAt": "2022년 7월 1일",
          "comment": "이거 길 가다가 주웠어요. 근데 제가 떨어뜨린 거였음!"
        },
        {
          "commentId": 2,
          "nickname": "ABCDEFU",
          "createdAt": "2022년 7월 1일",
          "comment": "이거 길 가다가 주웠어요. 근데 제가 떨어뜨린 거였음!"
        },
        {
          "commentId": 3,
          "nickname": "ABCDEFU",
          "createdAt": "2022년 7월 1일",
          "comment": "이거 길 가다가 주웠어요. 근데 제가 떨어뜨린 거였음!"
        }
      ]
    },
    {
      "title": "틴트",
      "district": "대명 9동",
      "imageURL": "https://image.zdnet.co.kr/2021/03/15/9a199a4f4d3770adff57ec09cfec4eb1.png",
      "content": "이 글은 엄청 긴 글 입니다. 진짜 길다니까요? 들어보세요. 긴 글이라고 하는데 왜 믿질 못하나요? 진짜 어이가 없네. 이 글은 엄청 긴 글 입니다. 진짜 길다니까요? 들어보세요. 긴 글이라고 하는데 왜 믿질 못하나요? 진짜 어이가 없네. 이 글은 엄청 긴 글 입니다. 진짜 길다니까요? 들어보세요. 긴 글이라고 하는데 왜 믿질 못하나요? 진짜 어이가 없네. 이 글은 엄청 긴 글 입니다. 진짜 길다니까요? 들어보세요. 긴 글이라고 하는데 왜 믿질 못하나요? 진짜 어이가 없네. ",
      "id": "BEJ0bFy",
      "gadaoda": "oda",
      "completed": true,
      "nickname": "맹구",
      "comments": [
        {
          "commentId": 1,
          "nickname": "ABCDEFU",
          "createdAt": "2022년 7월 1일",
          "comment": "이거 길 가다가 주웠어요. 근데 제가 떨어뜨린 거였음!"
        },
        {
          "commentId": 2,
          "nickname": "ABCDEFU",
          "createdAt": "2022년 7월 1일",
          "comment": "이거 길 가다가 주웠어요. 근데 제가 떨어뜨린 거였음!"
        },
        {
          "commentId": 3,
          "nickname": "ABCDEFU",
          "createdAt": "2022년 7월 1일",
          "comment": "이거 길 가다가 주웠어요. 근데 제가 떨어뜨린 거였음!"
        }
      ]
    },
    {
      "title": "가방",
      "district": "대명 9동",
      "imageURL": "https://image.zdnet.co.kr/2021/03/15/9a199a4f4d3770adff57ec09cfec4eb1.png",
      "content": "이 글은 엄청 긴 글 입니다. 진짜 길다니까요? 들어보세요. 긴 글이라고 하는데 왜 믿질 못하나요? 진짜 어이가 없네. 이 글은 엄청 긴 글 입니다. 진짜 길다니까요? 들어보세요. 긴 글이라고 하는데 왜 믿질 못하나요? 진짜 어이가 없네. 이 글은 엄청 긴 글 입니다. 진짜 길다니까요? 들어보세요. 긴 글이라고 하는데 왜 믿질 못하나요? 진짜 어이가 없네. 이 글은 엄청 긴 글 입니다. 진짜 길다니까요? 들어보세요. 긴 글이라고 하는데 왜 믿질 못하나요? 진짜 어이가 없네. ",
      "id": "W2081AW",
      "gadaoda": "oda",
      "completed": false,
      "nickname": "맹구",
      "comments": [
        {
          "commentId": 1,
          "nickname": "ABCDEFU",
          "createdAt": "2022년 7월 1일",
          "comment": "이거 길 가다가 주웠어요. 근데 제가 떨어뜨린 거였음!"
        },
        {
          "commentId": 2,
          "nickname": "ABCDEFU",
          "createdAt": "2022년 7월 1일",
          "comment": "이거 길 가다가 주웠어요. 근데 제가 떨어뜨린 거였음!"
        },
        {
          "commentId": 3,
          "nickname": "ABCDEFU",
          "createdAt": "2022년 7월 1일",
          "comment": "이거 길 가다가 주웠어요. 근데 제가 떨어뜨린 거였음!"
        }
      ]
    },
    {
      "title": "샤넬 핸드백",
      "district": "대명 9동",
      "imageURL": "https://image.zdnet.co.kr/2021/03/15/9a199a4f4d3770adff57ec09cfec4eb1.png",
      "content": "이 글은 엄청 긴 글 입니다. 진짜 길다니까요? 들어보세요. 긴 글이라고 하는데 왜 믿질 못하나요? 진짜 어이가 없네. 이 글은 엄청 긴 글 입니다. 진짜 길다니까요? 들어보세요. 긴 글이라고 하는데 왜 믿질 못하나요? 진짜 어이가 없네. 이 글은 엄청 긴 글 입니다. 진짜 길다니까요? 들어보세요. 긴 글이라고 하는데 왜 믿질 못하나요? 진짜 어이가 없네. 이 글은 엄청 긴 글 입니다. 진짜 길다니까요? 들어보세요. 긴 글이라고 하는데 왜 믿질 못하나요? 진짜 어이가 없네. ",
      "id": "rTdbg21",
      "gadaoda": "oda",
      "completed": true,
      "nickname": "맹구",
      "comments": [
        {
          "commentId": 1,
          "nickname": "ABCDEFU",
          "createdAt": "2022년 7월 1일",
          "comment": "이거 길 가다가 주웠어요. 근데 제가 떨어뜨린 거였음!"
        },
        {
          "commentId": 2,
          "nickname": "ABCDEFU",
          "createdAt": "2022년 7월 1일",
          "comment": "이거 길 가다가 주웠어요. 근데 제가 떨어뜨린 거였음!"
        },
        {
          "commentId": 3,
          "nickname": "ABCDEFU",
          "createdAt": "2022년 7월 1일",
          "comment": "이거 길 가다가 주웠어요. 근데 제가 떨어뜨린 거였음!"
        }
      ]
    },
    {
      "title": "몽블랑 카드지갑",
      "district": "대명 9동",
      "imageURL": "https://image.zdnet.co.kr/2021/03/15/9a199a4f4d3770adff57ec09cfec4eb1.png",
      "content": "이 글은 엄청 긴 글 입니다. 진짜 길다니까요? 들어보세요. 긴 글이라고 하는데 왜 믿질 못하나요? 진짜 어이가 없네. 이 글은 엄청 긴 글 입니다. 진짜 길다니까요? 들어보세요. 긴 글이라고 하는데 왜 믿질 못하나요? 진짜 어이가 없네. 이 글은 엄청 긴 글 입니다. 진짜 길다니까요? 들어보세요. 긴 글이라고 하는데 왜 믿질 못하나요? 진짜 어이가 없네. 이 글은 엄청 긴 글 입니다. 진짜 길다니까요? 들어보세요. 긴 글이라고 하는데 왜 믿질 못하나요? 진짜 어이가 없네. ",
      "id": "H3si0bx",
      "gadaoda": "gada",
      "completed": true,
      "nickname": "맹구",
      "comments": [
        {
          "commentId": 1,
          "nickname": "ABCDEFU",
          "createdAt": "2022년 7월 1일",
          "comment": "이거 길 가다가 주웠어요. 근데 제가 떨어뜨린 거였음!"
        },
        {
          "commentId": 2,
          "nickname": "ABCDEFU",
          "createdAt": "2022년 7월 1일",
          "comment": "이거 길 가다가 주웠어요. 근데 제가 떨어뜨린 거였음!"
        },
        {
          "commentId": 3,
          "nickname": "ABCDEFU",
          "createdAt": "2022년 7월 1일",
          "comment": "이거 길 가다가 주웠어요. 근데 제가 떨어뜨린 거였음!"
        }
      ]
    },
    {
      "title": "트랜치 코트",
      "district": "대명 9동",
      "imageURL": "https://image.zdnet.co.kr/2021/03/15/9a199a4f4d3770adff57ec09cfec4eb1.png",
      "content": "이 글은 엄청 긴 글 입니다. 진짜 길다니까요? 들어보세요. 긴 글이라고 하는데 왜 믿질 못하나요? 진짜 어이가 없네. 이 글은 엄청 긴 글 입니다. 진짜 길다니까요? 들어보세요. 긴 글이라고 하는데 왜 믿질 못하나요? 진짜 어이가 없네. 이 글은 엄청 긴 글 입니다. 진짜 길다니까요? 들어보세요. 긴 글이라고 하는데 왜 믿질 못하나요? 진짜 어이가 없네. 이 글은 엄청 긴 글 입니다. 진짜 길다니까요? 들어보세요. 긴 글이라고 하는데 왜 믿질 못하나요? 진짜 어이가 없네. ",
      "id": "Bd1ZriN",
      "gadaoda": "gada",
      "completed": true,
      "nickname": "맹구",
      "comments": [
        {
          "commentId": 1,
          "nickname": "ABCDEFU",
          "createdAt": "2022년 7월 1일",
          "comment": "이거 길 가다가 주웠어요. 근데 제가 떨어뜨린 거였음!"
        },
        {
          "commentId": 2,
          "nickname": "ABCDEFU",
          "createdAt": "2022년 7월 1일",
          "comment": "이거 길 가다가 주웠어요. 근데 제가 떨어뜨린 거였음!"
        },
        {
          "commentId": 3,
          "nickname": "ABCDEFU",
          "createdAt": "2022년 7월 1일",
          "comment": "이거 길 가다가 주웠어요. 근데 제가 떨어뜨린 거였음!"
        }
      ]
    },
    {
      "title": "트랜치 코트",
      "district": "대명 9동",
      "imageURL": "https://image.zdnet.co.kr/2021/03/15/9a199a4f4d3770adff57ec09cfec4eb1.png",
      "content": "이 글은 엄청 긴 글 입니다. 진짜 길다니까요? 들어보세요. 긴 글이라고 하는데 왜 믿질 못하나요? 진짜 어이가 없네. 이 글은 엄청 긴 글 입니다. 진짜 길다니까요? 들어보세요. 긴 글이라고 하는데 왜 믿질 못하나요? 진짜 어이가 없네. 이 글은 엄청 긴 글 입니다. 진짜 길다니까요? 들어보세요. 긴 글이라고 하는데 왜 믿질 못하나요? 진짜 어이가 없네. 이 글은 엄청 긴 글 입니다. 진짜 길다니까요? 들어보세요. 긴 글이라고 하는데 왜 믿질 못하나요? 진짜 어이가 없네. ",
      "id": "a8HDL9m",
      "gadaoda": "gada",
      "completed": false,
      "nickname": "맹구",
      "comments": [
        {
          "commentId": 1,
          "nickname": "ABCDEFU",
          "createdAt": "2022년 7월 1일",
          "comment": "이거 길 가다가 주웠어요. 근데 제가 떨어뜨린 거였음!"
        },
        {
          "commentId": 2,
          "nickname": "ABCDEFU",
          "createdAt": "2022년 7월 1일",
          "comment": "이거 길 가다가 주웠어요. 근데 제가 떨어뜨린 거였음!"
        },
        {
          "commentId": 3,
          "nickname": "ABCDEFU",
          "createdAt": "2022년 7월 1일",
          "comment": "이거 길 가다가 주웠어요. 근데 제가 떨어뜨린 거였음!"
        }
      ]
    },
    {
      "title": "나이키 바람막이",
      "district": "대명 9동",
      "imageURL": "https://image.zdnet.co.kr/2021/03/15/9a199a4f4d3770adff57ec09cfec4eb1.png",
      "content": "이 글은 엄청 긴 글 입니다. 진짜 길다니까요? 들어보세요. 긴 글이라고 하는데 왜 믿질 못하나요? 진짜 어이가 없네. 이 글은 엄청 긴 글 입니다. 진짜 길다니까요? 들어보세요. 긴 글이라고 하는데 왜 믿질 못하나요? 진짜 어이가 없네. 이 글은 엄청 긴 글 입니다. 진짜 길다니까요? 들어보세요. 긴 글이라고 하는데 왜 믿질 못하나요? 진짜 어이가 없네. 이 글은 엄청 긴 글 입니다. 진짜 길다니까요? 들어보세요. 긴 글이라고 하는데 왜 믿질 못하나요? 진짜 어이가 없네. ",
      "id": "AmX78t-",
      "gadaoda": "gada",
      "completed": false,
      "nickname": "맹구",
      "comments": [
        {
          "commentId": 1,
          "nickname": "ABCDEFU",
          "createdAt": "2022년 7월 1일",
          "comment": "이거 길 가다가 주웠어요. 근데 제가 떨어뜨린 거였음!"
        },
        {
          "commentId": 2,
          "nickname": "ABCDEFU",
          "createdAt": "2022년 7월 1일",
          "comment": "이거 길 가다가 주웠어요. 근데 제가 떨어뜨린 거였음!"
        },
        {
          "commentId": 3,
          "nickname": "ABCDEFU",
          "createdAt": "2022년 7월 1일",
          "comment": "이거 길 가다가 주웠어요. 근데 제가 떨어뜨린 거였음!"
        }
      ]
    },
    {
      "title": "빨간색 아디다스 슬리퍼",
      "district": "대명 9동",
      "imageURL": "https://image.zdnet.co.kr/2021/03/15/9a199a4f4d3770adff57ec09cfec4eb1.png",
      "content": "이 글은 엄청 긴 글 입니다. 진짜 길다니까요? 들어보세요. 긴 글이라고 하는데 왜 믿질 못하나요? 진짜 어이가 없네. 이 글은 엄청 긴 글 입니다. 진짜 길다니까요? 들어보세요. 긴 글이라고 하는데 왜 믿질 못하나요? 진짜 어이가 없네. 이 글은 엄청 긴 글 입니다. 진짜 길다니까요? 들어보세요. 긴 글이라고 하는데 왜 믿질 못하나요? 진짜 어이가 없네. 이 글은 엄청 긴 글 입니다. 진짜 길다니까요? 들어보세요. 긴 글이라고 하는데 왜 믿질 못하나요? 진짜 어이가 없네. ",
      "id": "C5gUrM_",
      "gadaoda": "oda",
      "completed": false,
      "nickname": "맹구",
      "comments": [
        {
          "commentId": 1,
          "nickname": "ABCDEFU",
          "createdAt": "2022년 7월 1일",
          "comment": "이거 길 가다가 주웠어요. 근데 제가 떨어뜨린 거였음!"
        },
        {
          "commentId": 2,
          "nickname": "ABCDEFU",
          "createdAt": "2022년 7월 1일",
          "comment": "이거 길 가다가 주웠어요. 근데 제가 떨어뜨린 거였음!"
        },
        {
          "commentId": 3,
          "nickname": "ABCDEFU",
          "createdAt": "2022년 7월 1일",
          "comment": "이거 길 가다가 주웠어요. 근데 제가 떨어뜨린 거였음!"
        }
      ]
    },
    {
      "title": "빨간색 아디다스 슬리퍼",
      "district": "대명 9동",
      "imageURL": "https://image.zdnet.co.kr/2021/03/15/9a199a4f4d3770adff57ec09cfec4eb1.png",
      "content": "이 글은 엄청 긴 글 입니다. 진짜 길다니까요? 들어보세요. 긴 글이라고 하는데 왜 믿질 못하나요? 진짜 어이가 없네. 이 글은 엄청 긴 글 입니다. 진짜 길다니까요? 들어보세요. 긴 글이라고 하는데 왜 믿질 못하나요? 진짜 어이가 없네. 이 글은 엄청 긴 글 입니다. 진짜 길다니까요? 들어보세요. 긴 글이라고 하는데 왜 믿질 못하나요? 진짜 어이가 없네. 이 글은 엄청 긴 글 입니다. 진짜 길다니까요? 들어보세요. 긴 글이라고 하는데 왜 믿질 못하나요? 진짜 어이가 없네. ",
      "id": "YZQbxIK",
      "gadaoda": "gada",
      "completed": true,
      "nickname": "맹구",
      "comments": [
        {
          "commentId": 1,
          "nickname": "ABCDEFU",
          "createdAt": "2022년 7월 1일",
          "comment": "이거 길 가다가 주웠어요. 근데 제가 떨어뜨린 거였음!"
        },
        {
          "commentId": 2,
          "nickname": "ABCDEFU",
          "createdAt": "2022년 7월 1일",
          "comment": "이거 길 가다가 주웠어요. 근데 제가 떨어뜨린 거였음!"
        },
        {
          "commentId": 3,
          "nickname": "ABCDEFU",
          "createdAt": "2022년 7월 1일",
          "comment": "이거 길 가다가 주웠어요. 근데 제가 떨어뜨린 거였음!"
        }
      ]
    },
    {
      "title": "빨간색 아디다스 슬리퍼",
      "district": "대명 9동",
      "imageURL": "https://image.zdnet.co.kr/2021/03/15/9a199a4f4d3770adff57ec09cfec4eb1.png",
      "content": "이 글은 엄청 긴 글 입니다. 진짜 길다니까요? 들어보세요. 긴 글이라고 하는데 왜 믿질 못하나요? 진짜 어이가 없네. 이 글은 엄청 긴 글 입니다. 진짜 길다니까요? 들어보세요. 긴 글이라고 하는데 왜 믿질 못하나요? 진짜 어이가 없네. 이 글은 엄청 긴 글 입니다. 진짜 길다니까요? 들어보세요. 긴 글이라고 하는데 왜 믿질 못하나요? 진짜 어이가 없네. 이 글은 엄청 긴 글 입니다. 진짜 길다니까요? 들어보세요. 긴 글이라고 하는데 왜 믿질 못하나요? 진짜 어이가 없네. ",
      "id": "E8VG32G",
      "gadaoda": "gada",
      "completed": false,
      "nickname": "맹구",
      "comments": [
        {
          "commentId": 1,
          "nickname": "ABCDEFU",
          "createdAt": "2022년 7월 1일",
          "comment": "이거 길 가다가 주웠어요. 근데 제가 떨어뜨린 거였음!"
        },
        {
          "commentId": 2,
          "nickname": "ABCDEFU",
          "createdAt": "2022년 7월 1일",
          "comment": "이거 길 가다가 주웠어요. 근데 제가 떨어뜨린 거였음!"
        },
        {
          "commentId": 3,
          "nickname": "ABCDEFU",
          "createdAt": "2022년 7월 1일",
          "comment": "이거 길 가다가 주웠어요. 근데 제가 떨어뜨린 거였음!"
        }
      ]
    },
    {
      "title": "슬리퍼",
      "district": "대명 9동",
      "imageURL": "https://image.zdnet.co.kr/2021/03/15/9a199a4f4d3770adff57ec09cfec4eb1.png",
      "content": "이 글은 엄청 긴 글 입니다. 진짜 길다니까요? 들어보세요. 긴 글이라고 하는데 왜 믿질 못하나요? 진짜 어이가 없네. 이 글은 엄청 긴 글 입니다. 진짜 길다니까요? 들어보세요. 긴 글이라고 하는데 왜 믿질 못하나요? 진짜 어이가 없네. 이 글은 엄청 긴 글 입니다. 진짜 길다니까요? 들어보세요. 긴 글이라고 하는데 왜 믿질 못하나요? 진짜 어이가 없네. 이 글은 엄청 긴 글 입니다. 진짜 길다니까요? 들어보세요. 긴 글이라고 하는데 왜 믿질 못하나요? 진짜 어이가 없네. ",
      "id": "jzFymDv",
      "gadaoda": "gada",
      "completed": true,
      "nickname": "맹구",
      "comments": [
        {
          "commentId": 1,
          "nickname": "ABCDEFU",
          "createdAt": "2022년 7월 1일",
          "comment": "이거 길 가다가 주웠어요. 근데 제가 떨어뜨린 거였음!"
        },
        {
          "commentId": 2,
          "nickname": "ABCDEFU",
          "createdAt": "2022년 7월 1일",
          "comment": "이거 길 가다가 주웠어요. 근데 제가 떨어뜨린 거였음!"
        },
        {
          "commentId": 3,
          "nickname": "ABCDEFU",
          "createdAt": "2022년 7월 1일",
          "comment": "이거 길 가다가 주웠어요. 근데 제가 떨어뜨린 거였음!"
        }
      ]
    },
    {
      "title": "슬리퍼",
      "district": "대명 9동",
      "imageURL": "https://image.zdnet.co.kr/2021/03/15/9a199a4f4d3770adff57ec09cfec4eb1.png",
      "content": "이 글은 엄청 긴 글 입니다. 진짜 길다니까요? 들어보세요. 긴 글이라고 하는데 왜 믿질 못하나요? 진짜 어이가 없네. 이 글은 엄청 긴 글 입니다. 진짜 길다니까요? 들어보세요. 긴 글이라고 하는데 왜 믿질 못하나요? 진짜 어이가 없네. 이 글은 엄청 긴 글 입니다. 진짜 길다니까요? 들어보세요. 긴 글이라고 하는데 왜 믿질 못하나요? 진짜 어이가 없네. 이 글은 엄청 긴 글 입니다. 진짜 길다니까요? 들어보세요. 긴 글이라고 하는데 왜 믿질 못하나요? 진짜 어이가 없네. ",
      "id": "3wzQj8R",
      "gadaoda": "gada",
      "completed": false,
      "nickname": "맹구",
      "comments": [
        {
          "commentId": 1,
          "nickname": "ABCDEFU",
          "createdAt": "2022년 7월 1일",
          "comment": "이거 길 가다가 주웠어요. 근데 제가 떨어뜨린 거였음!"
        },
        {
          "commentId": 2,
          "nickname": "ABCDEFU",
          "createdAt": "2022년 7월 1일",
          "comment": "이거 길 가다가 주웠어요. 근데 제가 떨어뜨린 거였음!"
        },
        {
          "commentId": 3,
          "nickname": "ABCDEFU",
          "createdAt": "2022년 7월 1일",
          "comment": "이거 길 가다가 주웠어요. 근데 제가 떨어뜨린 거였음!"
        }
      ]
    },
    {
      "title": "슬리퍼",
      "district": "대명 9동",
      "imageURL": "https://image.zdnet.co.kr/2021/03/15/9a199a4f4d3770adff57ec09cfec4eb1.png",
      "content": "이 글은 엄청 긴 글 입니다. 진짜 길다니까요? 들어보세요. 긴 글이라고 하는데 왜 믿질 못하나요? 진짜 어이가 없네. 이 글은 엄청 긴 글 입니다. 진짜 길다니까요? 들어보세요. 긴 글이라고 하는데 왜 믿질 못하나요? 진짜 어이가 없네. 이 글은 엄청 긴 글 입니다. 진짜 길다니까요? 들어보세요. 긴 글이라고 하는데 왜 믿질 못하나요? 진짜 어이가 없네. 이 글은 엄청 긴 글 입니다. 진짜 길다니까요? 들어보세요. 긴 글이라고 하는데 왜 믿질 못하나요? 진짜 어이가 없네. ",
      "id": "lTZGSSj",
      "gadaoda": "oda",
      "completed": false,
      "nickname": "맹구",
      "comments": [
        {
          "commentId": 1,
          "nickname": "ABCDEFU",
          "createdAt": "2022년 7월 1일",
          "comment": "이거 길 가다가 주웠어요. 근데 제가 떨어뜨린 거였음!"
        },
        {
          "commentId": 2,
          "nickname": "ABCDEFU",
          "createdAt": "2022년 7월 1일",
          "comment": "이거 길 가다가 주웠어요. 근데 제가 떨어뜨린 거였음!"
        },
        {
          "commentId": 3,
          "nickname": "ABCDEFU",
          "createdAt": "2022년 7월 1일",
          "comment": "이거 길 가다가 주웠어요. 근데 제가 떨어뜨린 거였음!"
        }
      ]
    },
    {
      "title": "티슈",
      "district": "대명 9동",
      "imageURL": "https://image.zdnet.co.kr/2021/03/15/9a199a4f4d3770adff57ec09cfec4eb1.png",
      "content": "이 글은 엄청 긴 글 입니다. 진짜 길다니까요? 들어보세요. 긴 글이라고 하는데 왜 믿질 못하나요? 진짜 어이가 없네. 이 글은 엄청 긴 글 입니다. 진짜 길다니까요? 들어보세요. 긴 글이라고 하는데 왜 믿질 못하나요? 진짜 어이가 없네. 이 글은 엄청 긴 글 입니다. 진짜 길다니까요? 들어보세요. 긴 글이라고 하는데 왜 믿질 못하나요? 진짜 어이가 없네. 이 글은 엄청 긴 글 입니다. 진짜 길다니까요? 들어보세요. 긴 글이라고 하는데 왜 믿질 못하나요? 진짜 어이가 없네. ",
      "id": "fvWFLy_",
      "gadaoda": "oda",
      "completed": true,
      "nickname": "맹구",
      "comments": [
        {
          "commentId": 1,
          "nickname": "ABCDEFU",
          "createdAt": "2022년 7월 1일",
          "comment": "이거 길 가다가 주웠어요. 근데 제가 떨어뜨린 거였음!"
        },
        {
          "commentId": 2,
          "nickname": "ABCDEFU",
          "createdAt": "2022년 7월 1일",
          "comment": "이거 길 가다가 주웠어요. 근데 제가 떨어뜨린 거였음!"
        },
        {
          "commentId": 3,
          "nickname": "ABCDEFU",
          "createdAt": "2022년 7월 1일",
          "comment": "이거 길 가다가 주웠어요. 근데 제가 떨어뜨린 거였음!"
        }
      ]
    },
    {
      "title": "티슈",
      "district": "대명 9동",
      "imageURL": "https://image.zdnet.co.kr/2021/03/15/9a199a4f4d3770adff57ec09cfec4eb1.png",
      "content": "이 글은 엄청 긴 글 입니다. 진짜 길다니까요? 들어보세요. 긴 글이라고 하는데 왜 믿질 못하나요? 진짜 어이가 없네. 이 글은 엄청 긴 글 입니다. 진짜 길다니까요? 들어보세요. 긴 글이라고 하는데 왜 믿질 못하나요? 진짜 어이가 없네. 이 글은 엄청 긴 글 입니다. 진짜 길다니까요? 들어보세요. 긴 글이라고 하는데 왜 믿질 못하나요? 진짜 어이가 없네. 이 글은 엄청 긴 글 입니다. 진짜 길다니까요? 들어보세요. 긴 글이라고 하는데 왜 믿질 못하나요? 진짜 어이가 없네. ",
      "id": "DoKf5jZ",
      "gadaoda": "oda",
      "completed": false,
      "nickname": "맹구",
      "comments": [
        {
          "commentId": 1,
          "nickname": "ABCDEFU",
          "createdAt": "2022년 7월 1일",
          "comment": "이거 길 가다가 주웠어요. 근데 제가 떨어뜨린 거였음!"
        },
        {
          "commentId": 2,
          "nickname": "ABCDEFU",
          "createdAt": "2022년 7월 1일",
          "comment": "이거 길 가다가 주웠어요. 근데 제가 떨어뜨린 거였음!"
        },
        {
          "commentId": 3,
          "nickname": "ABCDEFU",
          "createdAt": "2022년 7월 1일",
          "comment": "이거 길 가다가 주웠어요. 근데 제가 떨어뜨린 거였음!"
        }
      ]
    },
    {
      "title": "티슈",
      "district": "대명 9동",
      "imageURL": "https://image.zdnet.co.kr/2021/03/15/9a199a4f4d3770adff57ec09cfec4eb1.png",
      "content": "이 글은 엄청 긴 글 입니다. 진짜 길다니까요? 들어보세요. 긴 글이라고 하는데 왜 믿질 못하나요? 진짜 어이가 없네. 이 글은 엄청 긴 글 입니다. 진짜 길다니까요? 들어보세요. 긴 글이라고 하는데 왜 믿질 못하나요? 진짜 어이가 없네. 이 글은 엄청 긴 글 입니다. 진짜 길다니까요? 들어보세요. 긴 글이라고 하는데 왜 믿질 못하나요? 진짜 어이가 없네. 이 글은 엄청 긴 글 입니다. 진짜 길다니까요? 들어보세요. 긴 글이라고 하는데 왜 믿질 못하나요? 진짜 어이가 없네. ",
      "id": "s5j_NMn",
      "gadaoda": "oda",
      "completed": true,
      "nickname": "맹구",
      "comments": [
        {
          "commentId": 1,
          "nickname": "ABCDEFU",
          "createdAt": "2022년 7월 1일",
          "comment": "이거 길 가다가 주웠어요. 근데 제가 떨어뜨린 거였음!"
        },
        {
          "commentId": 2,
          "nickname": "ABCDEFU",
          "createdAt": "2022년 7월 1일",
          "comment": "이거 길 가다가 주웠어요. 근데 제가 떨어뜨린 거였음!"
        },
        {
          "commentId": 3,
          "nickname": "ABCDEFU",
          "createdAt": "2022년 7월 1일",
          "comment": "이거 길 가다가 주웠어요. 근데 제가 떨어뜨린 거였음!"
        }
      ]
    },
    {
      "title": "티슈",
      "district": "대명 9동",
      "imageURL": "https://image.zdnet.co.kr/2021/03/15/9a199a4f4d3770adff57ec09cfec4eb1.png",
      "content": "이 글은 엄청 긴 글 입니다. 진짜 길다니까요? 들어보세요. 긴 글이라고 하는데 왜 믿질 못하나요? 진짜 어이가 없네. 이 글은 엄청 긴 글 입니다. 진짜 길다니까요? 들어보세요. 긴 글이라고 하는데 왜 믿질 못하나요? 진짜 어이가 없네. 이 글은 엄청 긴 글 입니다. 진짜 길다니까요? 들어보세요. 긴 글이라고 하는데 왜 믿질 못하나요? 진짜 어이가 없네. 이 글은 엄청 긴 글 입니다. 진짜 길다니까요? 들어보세요. 긴 글이라고 하는데 왜 믿질 못하나요? 진짜 어이가 없네. ",
      "id": "gA7BJWP",
      "gadaoda": "oda",
      "completed": false,
      "nickname": "맹구",
      "comments": [
        {
          "commentId": 1,
          "nickname": "ABCDEFU",
          "createdAt": "2022년 7월 1일",
          "comment": "이거 길 가다가 주웠어요. 근데 제가 떨어뜨린 거였음!"
        },
        {
          "commentId": 2,
          "nickname": "ABCDEFU",
          "createdAt": "2022년 7월 1일",
          "comment": "이거 길 가다가 주웠어요. 근데 제가 떨어뜨린 거였음!"
        },
        {
          "commentId": 3,
          "nickname": "ABCDEFU",
          "createdAt": "2022년 7월 1일",
          "comment": "이거 길 가다가 주웠어요. 근데 제가 떨어뜨린 거였음!"
        }
      ]
    },
    {
      "title": "마우스",
      "district": "대명 9동",
      "imageURL": "https://image.zdnet.co.kr/2021/03/15/9a199a4f4d3770adff57ec09cfec4eb1.png",
      "content": "이 글은 엄청 긴 글 입니다. 진짜 길다니까요? 들어보세요. 긴 글이라고 하는데 왜 믿질 못하나요? 진짜 어이가 없네. 이 글은 엄청 긴 글 입니다. 진짜 길다니까요? 들어보세요. 긴 글이라고 하는데 왜 믿질 못하나요? 진짜 어이가 없네. 이 글은 엄청 긴 글 입니다. 진짜 길다니까요? 들어보세요. 긴 글이라고 하는데 왜 믿질 못하나요? 진짜 어이가 없네. 이 글은 엄청 긴 글 입니다. 진짜 길다니까요? 들어보세요. 긴 글이라고 하는데 왜 믿질 못하나요? 진짜 어이가 없네. ",
      "id": "k3PsiTV",
      "gadaoda": "gada",
      "completed": true,
      "nickname": "맹구",
      "comments": [
        {
          "commentId": 1,
          "nickname": "ABCDEFU",
          "createdAt": "2022년 7월 1일",
          "comment": "이거 길 가다가 주웠어요. 근데 제가 떨어뜨린 거였음!"
        },
        {
          "commentId": 2,
          "nickname": "ABCDEFU",
          "createdAt": "2022년 7월 1일",
          "comment": "이거 길 가다가 주웠어요. 근데 제가 떨어뜨린 거였음!"
        },
        {
          "commentId": 3,
          "nickname": "ABCDEFU",
          "createdAt": "2022년 7월 1일",
          "comment": "이거 길 가다가 주웠어요. 근데 제가 떨어뜨린 거였음!"
        }
      ]
    },
    {
      "title": "마우스",
      "district": "대명 9동",
      "imageURL": "https://image.zdnet.co.kr/2021/03/15/9a199a4f4d3770adff57ec09cfec4eb1.png",
      "content": "이 글은 엄청 긴 글 입니다. 진짜 길다니까요? 들어보세요. 긴 글이라고 하는데 왜 믿질 못하나요? 진짜 어이가 없네. 이 글은 엄청 긴 글 입니다. 진짜 길다니까요? 들어보세요. 긴 글이라고 하는데 왜 믿질 못하나요? 진짜 어이가 없네. 이 글은 엄청 긴 글 입니다. 진짜 길다니까요? 들어보세요. 긴 글이라고 하는데 왜 믿질 못하나요? 진짜 어이가 없네. 이 글은 엄청 긴 글 입니다. 진짜 길다니까요? 들어보세요. 긴 글이라고 하는데 왜 믿질 못하나요? 진짜 어이가 없네. ",
      "id": "rb8_qJv",
      "gadaoda": "gada",
      "completed": false,
      "nickname": "맹구",
      "comments": [
        {
          "commentId": 1,
          "nickname": "ABCDEFU",
          "createdAt": "2022년 7월 1일",
          "comment": "이거 길 가다가 주웠어요. 근데 제가 떨어뜨린 거였음!"
        },
        {
          "commentId": 2,
          "nickname": "ABCDEFU",
          "createdAt": "2022년 7월 1일",
          "comment": "이거 길 가다가 주웠어요. 근데 제가 떨어뜨린 거였음!"
        },
        {
          "commentId": 3,
          "nickname": "ABCDEFU",
          "createdAt": "2022년 7월 1일",
          "comment": "이거 길 가다가 주웠어요. 근데 제가 떨어뜨린 거였음!"
        }
      ]
    },
    {
      "title": "남명초등학교 1학년 2반 교과서",
      "district": "대명 9동",
      "imageURL": "https://image.zdnet.co.kr/2021/03/15/9a199a4f4d3770adff57ec09cfec4eb1.png",
      "content": "이 글은 엄청 긴 글 입니다. 진짜 길다니까요? 들어보세요. 긴 글이라고 하는데 왜 믿질 못하나요? 진짜 어이가 없네. 이 글은 엄청 긴 글 입니다. 진짜 길다니까요? 들어보세요. 긴 글이라고 하는데 왜 믿질 못하나요? 진짜 어이가 없네. 이 글은 엄청 긴 글 입니다. 진짜 길다니까요? 들어보세요. 긴 글이라고 하는데 왜 믿질 못하나요? 진짜 어이가 없네. 이 글은 엄청 긴 글 입니다. 진짜 길다니까요? 들어보세요. 긴 글이라고 하는데 왜 믿질 못하나요? 진짜 어이가 없네. ",
      "id": "6aIs9E4",
      "gadaoda": "gada",
      "completed": false,
      "nickname": "맹구",
      "comments": [
        {
          "commentId": 1,
          "nickname": "ABCDEFU",
          "createdAt": "2022년 7월 1일",
          "comment": "이거 길 가다가 주웠어요. 근데 제가 떨어뜨린 거였음!"
        },
        {
          "commentId": 2,
          "nickname": "ABCDEFU",
          "createdAt": "2022년 7월 1일",
          "comment": "이거 길 가다가 주웠어요. 근데 제가 떨어뜨린 거였음!"
        },
        {
          "commentId": 3,
          "nickname": "ABCDEFU",
          "createdAt": "2022년 7월 1일",
          "comment": "이거 길 가다가 주웠어요. 근데 제가 떨어뜨린 거였음!"
        }
      ]
    },
    {
      "title": "참고서",
      "district": "대명 9동",
      "imageURL": "https://image.zdnet.co.kr/2021/03/15/9a199a4f4d3770adff57ec09cfec4eb1.png",
      "content": "이 글은 엄청 긴 글 입니다. 진짜 길다니까요? 들어보세요. 긴 글이라고 하는데 왜 믿질 못하나요? 진짜 어이가 없네. 이 글은 엄청 긴 글 입니다. 진짜 길다니까요? 들어보세요. 긴 글이라고 하는데 왜 믿질 못하나요? 진짜 어이가 없네. 이 글은 엄청 긴 글 입니다. 진짜 길다니까요? 들어보세요. 긴 글이라고 하는데 왜 믿질 못하나요? 진짜 어이가 없네. 이 글은 엄청 긴 글 입니다. 진짜 길다니까요? 들어보세요. 긴 글이라고 하는데 왜 믿질 못하나요? 진짜 어이가 없네. ",
      "id": "IHjGfoi",
      "gadaoda": "gada",
      "completed": false,
      "nickname": "맹구",
      "comments": [
        {
          "commentId": 1,
          "nickname": "ABCDEFU",
          "createdAt": "2022년 7월 1일",
          "comment": "이거 길 가다가 주웠어요. 근데 제가 떨어뜨린 거였음!"
        },
        {
          "commentId": 2,
          "nickname": "ABCDEFU",
          "createdAt": "2022년 7월 1일",
          "comment": "이거 길 가다가 주웠어요. 근데 제가 떨어뜨린 거였음!"
        },
        {
          "commentId": 3,
          "nickname": "ABCDEFU",
          "createdAt": "2022년 7월 1일",
          "comment": "이거 길 가다가 주웠어요. 근데 제가 떨어뜨린 거였음!"
        }
      ]
    },
    {
      "title": "참고서",
      "district": "대명 9동",
      "imageURL": "https://image.zdnet.co.kr/2021/03/15/9a199a4f4d3770adff57ec09cfec4eb1.png",
      "content": "이 글은 엄청 긴 글 입니다. 진짜 길다니까요? 들어보세요. 긴 글이라고 하는데 왜 믿질 못하나요? 진짜 어이가 없네. 이 글은 엄청 긴 글 입니다. 진짜 길다니까요? 들어보세요. 긴 글이라고 하는데 왜 믿질 못하나요? 진짜 어이가 없네. 이 글은 엄청 긴 글 입니다. 진짜 길다니까요? 들어보세요. 긴 글이라고 하는데 왜 믿질 못하나요? 진짜 어이가 없네. 이 글은 엄청 긴 글 입니다. 진짜 길다니까요? 들어보세요. 긴 글이라고 하는데 왜 믿질 못하나요? 진짜 어이가 없네. ",
      "id": "xtvbHM5",
      "gadaoda": "gada",
      "completed": false,
      "nickname": "맹구",
      "comments": [
        {
          "commentId": 1,
          "nickname": "ABCDEFU",
          "createdAt": "2022년 7월 1일",
          "comment": "이거 길 가다가 주웠어요. 근데 제가 떨어뜨린 거였음!"
        },
        {
          "commentId": 2,
          "nickname": "ABCDEFU",
          "createdAt": "2022년 7월 1일",
          "comment": "이거 길 가다가 주웠어요. 근데 제가 떨어뜨린 거였음!"
        },
        {
          "commentId": 3,
          "nickname": "ABCDEFU",
          "createdAt": "2022년 7월 1일",
          "comment": "이거 길 가다가 주웠어요. 근데 제가 떨어뜨린 거였음!"
        }
      ]
    },
    {
      "title": "참고서",
      "district": "대명 9동",
      "imageURL": "https://image.zdnet.co.kr/2021/03/15/9a199a4f4d3770adff57ec09cfec4eb1.png",
      "content": "이 글은 엄청 긴 글 입니다. 진짜 길다니까요? 들어보세요. 긴 글이라고 하는데 왜 믿질 못하나요? 진짜 어이가 없네. 이 글은 엄청 긴 글 입니다. 진짜 길다니까요? 들어보세요. 긴 글이라고 하는데 왜 믿질 못하나요? 진짜 어이가 없네. 이 글은 엄청 긴 글 입니다. 진짜 길다니까요? 들어보세요. 긴 글이라고 하는데 왜 믿질 못하나요? 진짜 어이가 없네. 이 글은 엄청 긴 글 입니다. 진짜 길다니까요? 들어보세요. 긴 글이라고 하는데 왜 믿질 못하나요? 진짜 어이가 없네. ",
      "id": "C-tDRQG",
      "gadaoda": "gada",
      "completed": false,
      "nickname": "맹구",
      "comments": [
        {
          "commentId": 1,
          "nickname": "ABCDEFU",
          "createdAt": "2022년 7월 1일",
          "comment": "이거 길 가다가 주웠어요. 근데 제가 떨어뜨린 거였음!"
        },
        {
          "commentId": 2,
          "nickname": "ABCDEFU",
          "createdAt": "2022년 7월 1일",
          "comment": "이거 길 가다가 주웠어요. 근데 제가 떨어뜨린 거였음!"
        },
        {
          "commentId": 3,
          "nickname": "ABCDEFU",
          "createdAt": "2022년 7월 1일",
          "comment": "이거 길 가다가 주웠어요. 근데 제가 떨어뜨린 거였음!"
        }
      ]
    },
    {
      "title": "참고서",
      "district": "대명 9동",
      "imageURL": "https://image.zdnet.co.kr/2021/03/15/9a199a4f4d3770adff57ec09cfec4eb1.png",
      "content": "이 글은 엄청 긴 글 입니다. 진짜 길다니까요? 들어보세요. 긴 글이라고 하는데 왜 믿질 못하나요? 진짜 어이가 없네. 이 글은 엄청 긴 글 입니다. 진짜 길다니까요? 들어보세요. 긴 글이라고 하는데 왜 믿질 못하나요? 진짜 어이가 없네. 이 글은 엄청 긴 글 입니다. 진짜 길다니까요? 들어보세요. 긴 글이라고 하는데 왜 믿질 못하나요? 진짜 어이가 없네. 이 글은 엄청 긴 글 입니다. 진짜 길다니까요? 들어보세요. 긴 글이라고 하는데 왜 믿질 못하나요? 진짜 어이가 없네. ",
      "id": "5IwH9lv",
      "gadaoda": "gada",
      "completed": false,
      "nickname": "맹구",
      "comments": [
        {
          "commentId": 1,
          "nickname": "ABCDEFU",
          "createdAt": "2022년 7월 1일",
          "comment": "이거 길 가다가 주웠어요. 근데 제가 떨어뜨린 거였음!"
        },
        {
          "commentId": 2,
          "nickname": "ABCDEFU",
          "createdAt": "2022년 7월 1일",
          "comment": "이거 길 가다가 주웠어요. 근데 제가 떨어뜨린 거였음!"
        },
        {
          "commentId": 3,
          "nickname": "ABCDEFU",
          "createdAt": "2022년 7월 1일",
          "comment": "이거 길 가다가 주웠어요. 근데 제가 떨어뜨린 거였음!"
        }
      ]
    },
    {
      "title": "마우스 패드",
      "district": "대명 9동",
      "imageURL": "https://image.zdnet.co.kr/2021/03/15/9a199a4f4d3770adff57ec09cfec4eb1.png",
      "content": "이 글은 엄청 긴 글 입니다. 진짜 길다니까요? 들어보세요. 긴 글이라고 하는데 왜 믿질 못하나요? 진짜 어이가 없네. 이 글은 엄청 긴 글 입니다. 진짜 길다니까요? 들어보세요. 긴 글이라고 하는데 왜 믿질 못하나요? 진짜 어이가 없네. 이 글은 엄청 긴 글 입니다. 진짜 길다니까요? 들어보세요. 긴 글이라고 하는데 왜 믿질 못하나요? 진짜 어이가 없네. 이 글은 엄청 긴 글 입니다. 진짜 길다니까요? 들어보세요. 긴 글이라고 하는데 왜 믿질 못하나요? 진짜 어이가 없네. ",
      "id": "FJn3zqB",
      "gadaoda": "gada",
      "completed": false,
      "nickname": "맹구",
      "comments": [
        {
          "commentId": 1,
          "nickname": "ABCDEFU",
          "createdAt": "2022년 7월 1일",
          "comment": "이거 길 가다가 주웠어요. 근데 제가 떨어뜨린 거였음!"
        },
        {
          "commentId": 2,
          "nickname": "ABCDEFU",
          "createdAt": "2022년 7월 1일",
          "comment": "이거 길 가다가 주웠어요. 근데 제가 떨어뜨린 거였음!"
        },
        {
          "commentId": 3,
          "nickname": "ABCDEFU",
          "createdAt": "2022년 7월 1일",
          "comment": "이거 길 가다가 주웠어요. 근데 제가 떨어뜨린 거였음!"
        }
      ]
    },
    {
      "title": "오토바이 헬맷",
      "district": "대명 9동",
      "imageURL": "https://image.zdnet.co.kr/2021/03/15/9a199a4f4d3770adff57ec09cfec4eb1.png",
      "content": "이 글은 엄청 긴 글 입니다. 진짜 길다니까요? 들어보세요. 긴 글이라고 하는데 왜 믿질 못하나요? 진짜 어이가 없네. 이 글은 엄청 긴 글 입니다. 진짜 길다니까요? 들어보세요. 긴 글이라고 하는데 왜 믿질 못하나요? 진짜 어이가 없네. 이 글은 엄청 긴 글 입니다. 진짜 길다니까요? 들어보세요. 긴 글이라고 하는데 왜 믿질 못하나요? 진짜 어이가 없네. 이 글은 엄청 긴 글 입니다. 진짜 길다니까요? 들어보세요. 긴 글이라고 하는데 왜 믿질 못하나요? 진짜 어이가 없네. ",
      "id": "5hoDgiF",
      "gadaoda": "gada",
      "completed": false,
      "nickname": "맹구",
      "comments": [
        {
          "commentId": 1,
          "nickname": "ABCDEFU",
          "createdAt": "2022년 7월 1일",
          "comment": "이거 길 가다가 주웠어요. 근데 제가 떨어뜨린 거였음!"
        },
        {
          "commentId": 2,
          "nickname": "ABCDEFU",
          "createdAt": "2022년 7월 1일",
          "comment": "이거 길 가다가 주웠어요. 근데 제가 떨어뜨린 거였음!"
        },
        {
          "commentId": 3,
          "nickname": "ABCDEFU",
          "createdAt": "2022년 7월 1일",
          "comment": "이거 길 가다가 주웠어요. 근데 제가 떨어뜨린 거였음!"
        }
      ]
    },
    {
      "title": "오토바이 헬맷",
      "district": "대명 9동",
      "imageURL": "https://image.zdnet.co.kr/2021/03/15/9a199a4f4d3770adff57ec09cfec4eb1.png",
      "content": "이 글은 엄청 긴 글 입니다. 진짜 길다니까요? 들어보세요. 긴 글이라고 하는데 왜 믿질 못하나요? 진짜 어이가 없네. 이 글은 엄청 긴 글 입니다. 진짜 길다니까요? 들어보세요. 긴 글이라고 하는데 왜 믿질 못하나요? 진짜 어이가 없네. 이 글은 엄청 긴 글 입니다. 진짜 길다니까요? 들어보세요. 긴 글이라고 하는데 왜 믿질 못하나요? 진짜 어이가 없네. 이 글은 엄청 긴 글 입니다. 진짜 길다니까요? 들어보세요. 긴 글이라고 하는데 왜 믿질 못하나요? 진짜 어이가 없네. ",
      "id": "ugaL4o9",
      "gadaoda": "gada",
      "completed": false,
      "nickname": "맹구",
      "comments": [
        {
          "commentId": 1,
          "nickname": "ABCDEFU",
          "createdAt": "2022년 7월 1일",
          "comment": "이거 길 가다가 주웠어요. 근데 제가 떨어뜨린 거였음!"
        },
        {
          "commentId": 2,
          "nickname": "ABCDEFU",
          "createdAt": "2022년 7월 1일",
          "comment": "이거 길 가다가 주웠어요. 근데 제가 떨어뜨린 거였음!"
        },
        {
          "commentId": 3,
          "nickname": "ABCDEFU",
          "createdAt": "2022년 7월 1일",
          "comment": "이거 길 가다가 주웠어요. 근데 제가 떨어뜨린 거였음!"
        }
      ]
    },
    {
      "title": "알톤 자전거",
      "district": "대명 9동",
      "imageURL": "https://image.zdnet.co.kr/2021/03/15/9a199a4f4d3770adff57ec09cfec4eb1.png",
      "content": "이 글은 엄청 긴 글 입니다. 진짜 길다니까요? 들어보세요. 긴 글이라고 하는데 왜 믿질 못하나요? 진짜 어이가 없네. 이 글은 엄청 긴 글 입니다. 진짜 길다니까요? 들어보세요. 긴 글이라고 하는데 왜 믿질 못하나요? 진짜 어이가 없네. 이 글은 엄청 긴 글 입니다. 진짜 길다니까요? 들어보세요. 긴 글이라고 하는데 왜 믿질 못하나요? 진짜 어이가 없네. 이 글은 엄청 긴 글 입니다. 진짜 길다니까요? 들어보세요. 긴 글이라고 하는데 왜 믿질 못하나요? 진짜 어이가 없네. ",
      "id": "o4rL8a7",
      "gadaoda": "oda",
      "completed": false,
      "nickname": "맹구",
      "comments": [
        {
          "commentId": 1,
          "nickname": "ABCDEFU",
          "createdAt": "2022년 7월 1일",
          "comment": "이거 길 가다가 주웠어요. 근데 제가 떨어뜨린 거였음!"
        },
        {
          "commentId": 2,
          "nickname": "ABCDEFU",
          "createdAt": "2022년 7월 1일",
          "comment": "이거 길 가다가 주웠어요. 근데 제가 떨어뜨린 거였음!"
        },
        {
          "commentId": 3,
          "nickname": "ABCDEFU",
          "createdAt": "2022년 7월 1일",
          "comment": "이거 길 가다가 주웠어요. 근데 제가 떨어뜨린 거였음!"
        }
      ]
    },
    {
      "title": "알톤 자전거",
      "district": "대명 9동",
      "imageURL": "https://image.zdnet.co.kr/2021/03/15/9a199a4f4d3770adff57ec09cfec4eb1.png",
      "content": "이 글은 엄청 긴 글 입니다. 진짜 길다니까요? 들어보세요. 긴 글이라고 하는데 왜 믿질 못하나요? 진짜 어이가 없네. 이 글은 엄청 긴 글 입니다. 진짜 길다니까요? 들어보세요. 긴 글이라고 하는데 왜 믿질 못하나요? 진짜 어이가 없네. 이 글은 엄청 긴 글 입니다. 진짜 길다니까요? 들어보세요. 긴 글이라고 하는데 왜 믿질 못하나요? 진짜 어이가 없네. 이 글은 엄청 긴 글 입니다. 진짜 길다니까요? 들어보세요. 긴 글이라고 하는데 왜 믿질 못하나요? 진짜 어이가 없네. ",
      "id": "JHszcxR",
      "gadaoda": "oda",
      "completed": false,
      "nickname": "맹구",
      "comments": [
        {
          "commentId": 1,
          "nickname": "ABCDEFU",
          "createdAt": "2022년 7월 1일",
          "comment": "이거 길 가다가 주웠어요. 근데 제가 떨어뜨린 거였음!"
        },
        {
          "commentId": 2,
          "nickname": "ABCDEFU",
          "createdAt": "2022년 7월 1일",
          "comment": "이거 길 가다가 주웠어요. 근데 제가 떨어뜨린 거였음!"
        },
        {
          "commentId": 3,
          "nickname": "ABCDEFU",
          "createdAt": "2022년 7월 1일",
          "comment": "이거 길 가다가 주웠어요. 근데 제가 떨어뜨린 거였음!"
        }
      ]
    },
    {
      "title": "깁슨 기타",
      "district": "대명 9동",
      "imageURL": "https://image.zdnet.co.kr/2021/03/15/9a199a4f4d3770adff57ec09cfec4eb1.png",
      "content": "이 글은 엄청 긴 글 입니다. 진짜 길다니까요? 들어보세요. 긴 글이라고 하는데 왜 믿질 못하나요? 진짜 어이가 없네. 이 글은 엄청 긴 글 입니다. 진짜 길다니까요? 들어보세요. 긴 글이라고 하는데 왜 믿질 못하나요? 진짜 어이가 없네. 이 글은 엄청 긴 글 입니다. 진짜 길다니까요? 들어보세요. 긴 글이라고 하는데 왜 믿질 못하나요? 진짜 어이가 없네. 이 글은 엄청 긴 글 입니다. 진짜 길다니까요? 들어보세요. 긴 글이라고 하는데 왜 믿질 못하나요? 진짜 어이가 없네. ",
      "id": "X0Ib5fd",
      "gadaoda": "oda",
      "completed": false,
      "nickname": "맹구",
      "comments": [
        {
          "commentId": 1,
          "nickname": "ABCDEFU",
          "createdAt": "2022년 7월 1일",
          "comment": "이거 길 가다가 주웠어요. 근데 제가 떨어뜨린 거였음!"
        },
        {
          "commentId": 2,
          "nickname": "ABCDEFU",
          "createdAt": "2022년 7월 1일",
          "comment": "이거 길 가다가 주웠어요. 근데 제가 떨어뜨린 거였음!"
        },
        {
          "commentId": 3,
          "nickname": "ABCDEFU",
          "createdAt": "2022년 7월 1일",
          "comment": "이거 길 가다가 주웠어요. 근데 제가 떨어뜨린 거였음!"
        }
      ]
    },
    {
      "title": "깁슨 기타",
      "district": "대명 9동",
      "imageURL": "https://image.zdnet.co.kr/2021/03/15/9a199a4f4d3770adff57ec09cfec4eb1.png",
      "content": "이 글은 엄청 긴 글 입니다. 진짜 길다니까요? 들어보세요. 긴 글이라고 하는데 왜 믿질 못하나요? 진짜 어이가 없네. 이 글은 엄청 긴 글 입니다. 진짜 길다니까요? 들어보세요. 긴 글이라고 하는데 왜 믿질 못하나요? 진짜 어이가 없네. 이 글은 엄청 긴 글 입니다. 진짜 길다니까요? 들어보세요. 긴 글이라고 하는데 왜 믿질 못하나요? 진짜 어이가 없네. 이 글은 엄청 긴 글 입니다. 진짜 길다니까요? 들어보세요. 긴 글이라고 하는데 왜 믿질 못하나요? 진짜 어이가 없네. ",
      "id": "SOQ-4OC",
      "gadaoda": "gada",
      "completed": false,
      "nickname": "맹구",
      "comments": [
        {
          "commentId": 1,
          "nickname": "ABCDEFU",
          "createdAt": "2022년 7월 1일",
          "comment": "이거 길 가다가 주웠어요. 근데 제가 떨어뜨린 거였음!"
        },
        {
          "commentId": 2,
          "nickname": "ABCDEFU",
          "createdAt": "2022년 7월 1일",
          "comment": "이거 길 가다가 주웠어요. 근데 제가 떨어뜨린 거였음!"
        },
        {
          "commentId": 3,
          "nickname": "ABCDEFU",
          "createdAt": "2022년 7월 1일",
          "comment": "이거 길 가다가 주웠어요. 근데 제가 떨어뜨린 거였음!"
        }
      ]
    },
    {
      "title": "키보드 덮개",
      "district": "대명 9동",
      "imageURL": "https://image.zdnet.co.kr/2021/03/15/9a199a4f4d3770adff57ec09cfec4eb1.png",
      "content": "이 글은 엄청 긴 글 입니다. 진짜 길다니까요? 들어보세요. 긴 글이라고 하는데 왜 믿질 못하나요? 진짜 어이가 없네. 이 글은 엄청 긴 글 입니다. 진짜 길다니까요? 들어보세요. 긴 글이라고 하는데 왜 믿질 못하나요? 진짜 어이가 없네. 이 글은 엄청 긴 글 입니다. 진짜 길다니까요? 들어보세요. 긴 글이라고 하는데 왜 믿질 못하나요? 진짜 어이가 없네. 이 글은 엄청 긴 글 입니다. 진짜 길다니까요? 들어보세요. 긴 글이라고 하는데 왜 믿질 못하나요? 진짜 어이가 없네. ",
      "id": "CBJ_GIv",
      "gadaoda": "gada",
      "completed": false,
      "nickname": "맹구",
      "comments": [
        {
          "commentId": 1,
          "nickname": "ABCDEFU",
          "createdAt": "2022년 7월 1일",
          "comment": "이거 길 가다가 주웠어요. 근데 제가 떨어뜨린 거였음!"
        },
        {
          "commentId": 2,
          "nickname": "ABCDEFU",
          "createdAt": "2022년 7월 1일",
          "comment": "이거 길 가다가 주웠어요. 근데 제가 떨어뜨린 거였음!"
        },
        {
          "commentId": 3,
          "nickname": "ABCDEFU",
          "createdAt": "2022년 7월 1일",
          "comment": "이거 길 가다가 주웠어요. 근데 제가 떨어뜨린 거였음!"
        }
      ]
    },
    {
      "title": "키보드 덮개",
      "district": "대명 9동",
      "imageURL": "https://image.zdnet.co.kr/2021/03/15/9a199a4f4d3770adff57ec09cfec4eb1.png",
      "content": "이 글은 엄청 긴 글 입니다. 진짜 길다니까요? 들어보세요. 긴 글이라고 하는데 왜 믿질 못하나요? 진짜 어이가 없네. 이 글은 엄청 긴 글 입니다. 진짜 길다니까요? 들어보세요. 긴 글이라고 하는데 왜 믿질 못하나요? 진짜 어이가 없네. 이 글은 엄청 긴 글 입니다. 진짜 길다니까요? 들어보세요. 긴 글이라고 하는데 왜 믿질 못하나요? 진짜 어이가 없네. 이 글은 엄청 긴 글 입니다. 진짜 길다니까요? 들어보세요. 긴 글이라고 하는데 왜 믿질 못하나요? 진짜 어이가 없네. ",
      "id": "_-0BsTw",
      "gadaoda": "oda",
      "completed": false,
      "nickname": "맹구",
      "comments": [
        {
          "commentId": 1,
          "nickname": "ABCDEFU",
          "createdAt": "2022년 7월 1일",
          "comment": "이거 길 가다가 주웠어요. 근데 제가 떨어뜨린 거였음!"
        },
        {
          "commentId": 2,
          "nickname": "ABCDEFU",
          "createdAt": "2022년 7월 1일",
          "comment": "이거 길 가다가 주웠어요. 근데 제가 떨어뜨린 거였음!"
        },
        {
          "commentId": 3,
          "nickname": "ABCDEFU",
          "createdAt": "2022년 7월 1일",
          "comment": "이거 길 가다가 주웠어요. 근데 제가 떨어뜨린 거였음!"
        }
      ]
    },
    {
      "title": "키보드 덮개",
      "district": "대명 9동",
      "imageURL": "https://image.zdnet.co.kr/2021/03/15/9a199a4f4d3770adff57ec09cfec4eb1.png",
      "content": "이 글은 엄청 긴 글 입니다. 진짜 길다니까요? 들어보세요. 긴 글이라고 하는데 왜 믿질 못하나요? 진짜 어이가 없네. 이 글은 엄청 긴 글 입니다. 진짜 길다니까요? 들어보세요. 긴 글이라고 하는데 왜 믿질 못하나요? 진짜 어이가 없네. 이 글은 엄청 긴 글 입니다. 진짜 길다니까요? 들어보세요. 긴 글이라고 하는데 왜 믿질 못하나요? 진짜 어이가 없네. 이 글은 엄청 긴 글 입니다. 진짜 길다니까요? 들어보세요. 긴 글이라고 하는데 왜 믿질 못하나요? 진짜 어이가 없네. ",
      "id": "a490v54_e3ic8v6h",
      "gadaoda": "gada",
      "completed": false,
      "nickname": "맹구",
      "comments": [
        {
          "commentId": 1,
          "nickname": "ABCDEFU",
          "createdAt": "2022년 7월 1일",
          "comment": "이거 길 가다가 주웠어요. 근데 제가 떨어뜨린 거였음!"
        },
        {
          "commentId": 2,
          "nickname": "ABCDEFU",
          "createdAt": "2022년 7월 1일",
          "comment": "이거 길 가다가 주웠어요. 근데 제가 떨어뜨린 거였음!"
        },
        {
          "commentId": 3,
          "nickname": "ABCDEFU",
          "createdAt": "2022년 7월 1일",
          "comment": "이거 길 가다가 주웠어요. 근데 제가 떨어뜨린 거였음!"
        }
      ]
    }
  ]
}
